{
    "@id": "https://diyhistory.org/toyo/omekac3/api/298.json",
    "added": "2021-02-10T14:05:05+00:00",
    "element_texts": [
        {
            "element": {
                "id": 50,
                "name": "Title",
                "resource": "elements",
                "url": "https://diyhistory.org/toyo/omekac3/api/elements/50"
            },
            "element_set": {
                "id": 1,
                "name": "Dublin Core",
                "resource": "element_sets",
                "url": "https://diyhistory.org/toyo/omekac3/api/element_sets/1"
            },
            "html": false,
            "text": "ZJG048苦竹熟料竹料 観察ポイント2"
        },
        {
            "element": {
                "id": 48,
                "name": "Source",
                "resource": "elements",
                "url": "https://diyhistory.org/toyo/omekac3/api/elements/48"
            },
            "element_set": {
                "id": 1,
                "name": "Dublin Core",
                "resource": "element_sets",
                "url": "https://diyhistory.org/toyo/omekac3/api/element_sets/1"
            },
            "html": false,
            "text": "https://diyhistory.org/toyo/toyo3/iiif/2/ZJG048-2/manifest"
        },
        {
            "element": {
                "id": 45,
                "name": "Publisher",
                "resource": "elements",
                "url": "https://diyhistory.org/toyo/omekac3/api/elements/45"
            },
            "element_set": {
                "id": 1,
                "name": "Dublin Core",
                "resource": "element_sets",
                "url": "https://diyhistory.org/toyo/omekac3/api/element_sets/1"
            },
            "html": false,
            "text": "Provided by Example Organization"
        },
        {
            "element": {
                "id": 57,
                "name": "Original @id",
                "resource": "elements",
                "url": "https://diyhistory.org/toyo/omekac3/api/elements/57"
            },
            "element_set": {
                "id": 6,
                "name": "IIIF Collection Metadata",
                "resource": "element_sets",
                "url": "https://diyhistory.org/toyo/omekac3/api/element_sets/6"
            },
            "html": false,
            "text": "https://diyhistory.org/toyo/toyo3/iiif/2/ZJG048-2/manifest"
        },
        {
            "element": {
                "id": 60,
                "name": "JSON Data",
                "resource": "elements",
                "url": "https://diyhistory.org/toyo/omekac3/api/elements/60"
            },
            "element_set": {
                "id": 6,
                "name": "IIIF Collection Metadata",
                "resource": "element_sets",
                "url": "https://diyhistory.org/toyo/omekac3/api/element_sets/6"
            },
            "html": false,
            "text": "{\"@context\":\"http://iiif.io/api/presentation/2/context.json\",\"@id\":\"https://diyhistory.org/toyo/toyo3/iiif/2/ZJG048-2/manifest\",\"@type\":\"sc:Manifest\",\"label\":\"ZJG048\\u82e6\\u7af9\\u719f\\u6599\\u7af9\\u6599 \\u89b3\\u5bdf\\u30dd\\u30a4\\u30f3\\u30c82\",\"thumbnail\":{\"@id\":\"https://diyhistory.org/toyo/toyo3/files/medium/f48bb767619e83ecf3392e07e45b30f872113427.jpg\",\"@type\":\"dctypes:Image\",\"format\":\"image/jpeg\",\"width\":200,\"height\":150},\"attribution\":\"Provided by Example Organization\",\"related\":{\"@id\":\"https://diyhistory.org/toyo/toyo3\",\"format\":\"text/html\"},\"seeAlso\":{\"@id\":\"https://diyhistory.org/toyo/toyo3/api/items/372\",\"format\":\"application/ld+json\"},\"metadata\":[{\"label\":\"Title\",\"value\":\"ZJG048\\u82e6\\u7af9\\u719f\\u6599\\u7af9\\u6599 \\u89b3\\u5bdf\\u30dd\\u30a4\\u30f3\\u30c82\"},{\"label\":\"Identifier\",\"value\":[\"ZJG048-2\",\"ZJG048-2\"]},{\"label\":\"Relation\",\"value\":\"<a class=\\\"resource-link\\\" href=\\\"https://diyhistory.org/toyo/toyo3\\\"><span class=\\\"resource-name\\\">ZJG048\\u82e6\\u7af9\\u719f\\u6599\\u7af9\\u6599</span></a>\"}],\"sequences\":[{\"@id\":\"https://diyhistory.org/toyo/toyo3/iiif/2/ZJG048-2/sequence/normal\",\"@type\":\"sc:Sequence\",\"label\":\"Current Page Order\",\"viewingDirection\":\"left-to-right\",\"canvases\":[{\"@id\":\"https://diyhistory.org/toyo/toyo3/iiif/2/ZJG048-2/canvas/p1\",\"@type\":\"sc:Canvas\",\"label\":{\"type\":\"literal\",\"property_id\":1,\"property_label\":\"Title\",\"is_public\":true,\"@value\":\"ZJG048\\u00d720-2\"},\"thumbnail\":{\"@id\":\"https://diyhistory.org/toyo/toyo3/files/medium/f48bb767619e83ecf3392e07e45b30f872113427.jpg\",\"@type\":\"dctypes:Image\",\"format\":\"image/jpeg\",\"width\":200,\"height\":150},\"width\":1440,\"height\":1080,\"images\":[{\"@id\":\"https://diyhistory.org/toyo/toyo3/iiif/2/ZJG048-2/annotation/p0001-image\",\"@type\":\"oa:Annotation\",\"motivation\":\"sc:painting\",\"resource\":{\"@id\":\"https://diyhistory.org/toyo/toyo3/iiif-img/2/5079/full/800,600/0/default.jpg\",\"@type\":\"dctypes:Image\",\"format\":\"image/jpeg\",\"width\":1440,\"height\":1080,\"service\":{\"@context\":\"http://iiif.io/api/image/2/context.json\",\"@id\":\"https://diyhistory.org/toyo/toyo3/iiif-img/2/5079\",\"profile\":\"http://iiif.io/api/image/2/level2.json\"}},\"on\":\"https://diyhistory.org/toyo/toyo3/iiif/2/ZJG048-2/canvas/p1\"}],\"metadata\":[{\"label\":\"Title\",\"value\":\"ZJG048\\u00d720-2\"},{\"label\":\"Extent\",\"value\":\"20\"}]},{\"@id\":\"https://diyhistory.org/toyo/toyo3/iiif/2/ZJG048-2/canvas/p2\",\"@type\":\"sc:Canvas\",\"label\":{\"type\":\"literal\",\"property_id\":1,\"property_label\":\"Title\",\"is_public\":true,\"@value\":\"ZJG048\\u00d750-2\"},\"thumbnail\":{\"@id\":\"https://diyhistory.org/toyo/toyo3/files/medium/e18d5c317060d68d173f7f1ca0c50544ac1f7222.jpg\",\"@type\":\"dctypes:Image\",\"format\":\"image/jpeg\",\"width\":200,\"height\":150},\"width\":1440,\"height\":1080,\"images\":[{\"@id\":\"https://diyhistory.org/toyo/toyo3/iiif/2/ZJG048-2/annotation/p0002-image\",\"@type\":\"oa:Annotation\",\"motivation\":\"sc:painting\",\"resource\":{\"@id\":\"https://diyhistory.org/toyo/toyo3/iiif-img/2/5080/full/800,600/0/default.jpg\",\"@type\":\"dctypes:Image\",\"format\":\"image/jpeg\",\"width\":1440,\"height\":1080,\"service\":{\"@context\":\"http://iiif.io/api/image/2/context.json\",\"@id\":\"https://diyhistory.org/toyo/toyo3/iiif-img/2/5080\",\"profile\":\"http://iiif.io/api/image/2/level2.json\"}},\"on\":\"https://diyhistory.org/toyo/toyo3/iiif/2/ZJG048-2/canvas/p2\"}],\"metadata\":[{\"label\":\"Title\",\"value\":\"ZJG048\\u00d750-2\"},{\"label\":\"Extent\",\"value\":\"50\"}]},{\"@id\":\"https://diyhistory.org/toyo/toyo3/iiif/2/ZJG048-2/canvas/p3\",\"@type\":\"sc:Canvas\",\"label\":{\"type\":\"literal\",\"property_id\":1,\"property_label\":\"Title\",\"is_public\":true,\"@value\":\"ZJG048\\u00d7100-2\"},\"thumbnail\":{\"@id\":\"https://diyhistory.org/toyo/toyo3/files/medium/466e34895552524eef108a6b7e34eba452af028b.jpg\",\"@type\":\"dctypes:Image\",\"format\":\"image/jpeg\",\"width\":200,\"height\":150},\"width\":1440,\"height\":1080,\"images\":[{\"@id\":\"https://diyhistory.org/toyo/toyo3/iiif/2/ZJG048-2/annotation/p0003-image\",\"@type\":\"oa:Annotation\",\"motivation\":\"sc:painting\",\"resource\":{\"@id\":\"https://diyhistory.org/toyo/toyo3/iiif-img/2/5081/full/800,600/0/default.jpg\",\"@type\":\"dctypes:Image\",\"format\":\"image/jpeg\",\"width\":1440,\"height\":1080,\"service\":{\"@context\":\"http://iiif.io/api/image/2/context.json\",\"@id\":\"https://diyhistory.org/toyo/toyo3/iiif-img/2/5081\",\"profile\":\"http://iiif.io/api/image/2/level2.json\"}},\"on\":\"https://diyhistory.org/toyo/toyo3/iiif/2/ZJG048-2/canvas/p3\"}],\"metadata\":[{\"label\":\"Title\",\"value\":\"ZJG048\\u00d7100-2\"},{\"label\":\"Extent\",\"value\":\"100\"}]},{\"@id\":\"https://diyhistory.org/toyo/toyo3/iiif/2/ZJG048-2/canvas/p4\",\"@type\":\"sc:Canvas\",\"label\":{\"type\":\"literal\",\"property_id\":1,\"property_label\":\"Title\",\"is_public\":true,\"@value\":\"ZJG048\\u00d7200-2-3D\"},\"thumbnail\":{\"@id\":\"https://diyhistory.org/toyo/toyo3/files/medium/20a0cdb548db4248b7582d628b207e62e4d7a95b.jpg\",\"@type\":\"dctypes:Image\",\"format\":\"image/jpeg\",\"width\":200,\"height\":150},\"width\":1440,\"height\":1080,\"images\":[{\"@id\":\"https://diyhistory.org/toyo/toyo3/iiif/2/ZJG048-2/annotation/p0004-image\",\"@type\":\"oa:Annotation\",\"motivation\":\"sc:painting\",\"resource\":{\"@id\":\"https://diyhistory.org/toyo/toyo3/iiif-img/2/5082/full/800,600/0/default.jpg\",\"@type\":\"dctypes:Image\",\"format\":\"image/jpeg\",\"width\":1440,\"height\":1080,\"service\":{\"@context\":\"http://iiif.io/api/image/2/context.json\",\"@id\":\"https://diyhistory.org/toyo/toyo3/iiif-img/2/5082\",\"profile\":\"http://iiif.io/api/image/2/level2.json\"}},\"on\":\"https://diyhistory.org/toyo/toyo3/iiif/2/ZJG048-2/canvas/p4\"}],\"metadata\":[{\"label\":\"Title\",\"value\":\"ZJG048\\u00d7200-2-3D\"},{\"label\":\"Extent\",\"value\":\"200\"}]},{\"@id\":\"https://diyhistory.org/toyo/toyo3/iiif/2/ZJG048-2/canvas/p5\",\"@type\":\"sc:Canvas\",\"label\":{\"type\":\"literal\",\"property_id\":1,\"property_label\":\"Title\",\"is_public\":true,\"@value\":\"ZJG048\\u00d7200-2-3Dsca\"},\"thumbnail\":{\"@id\":\"https://diyhistory.org/toyo/toyo3/files/medium/8b18c77e3b9cb5d7070af0c19827c8b280589e56.jpg\",\"@type\":\"dctypes:Image\",\"format\":\"image/jpeg\",\"width\":200,\"height\":150},\"width\":1440,\"height\":1080,\"images\":[{\"@id\":\"https://diyhistory.org/toyo/toyo3/iiif/2/ZJG048-2/annotation/p0005-image\",\"@type\":\"oa:Annotation\",\"motivation\":\"sc:painting\",\"resource\":{\"@id\":\"https://diyhistory.org/toyo/toyo3/iiif-img/2/5083/full/800,600/0/default.jpg\",\"@type\":\"dctypes:Image\",\"format\":\"image/jpeg\",\"width\":1440,\"height\":1080,\"service\":{\"@context\":\"http://iiif.io/api/image/2/context.json\",\"@id\":\"https://diyhistory.org/toyo/toyo3/iiif-img/2/5083\",\"profile\":\"http://iiif.io/api/image/2/level2.json\"}},\"on\":\"https://diyhistory.org/toyo/toyo3/iiif/2/ZJG048-2/canvas/p5\"}],\"metadata\":[{\"label\":\"Title\",\"value\":\"ZJG048\\u00d7200-2-3Dsca\"},{\"label\":\"Extent\",\"value\":\"200\"}]},{\"@id\":\"https://diyhistory.org/toyo/toyo3/iiif/2/ZJG048-2/canvas/p6\",\"@type\":\"sc:Canvas\",\"label\":{\"type\":\"literal\",\"property_id\":1,\"property_label\":\"Title\",\"is_public\":true,\"@value\":\"ZJG048\\u00d7200-2-3to2D\"},\"thumbnail\":{\"@id\":\"https://diyhistory.org/toyo/toyo3/files/medium/8027a70c7e435dd1b51651e664a416b534b0b0e6.jpg\",\"@type\":\"dctypes:Image\",\"format\":\"image/jpeg\",\"width\":200,\"height\":150},\"width\":1440,\"height\":1080,\"images\":[{\"@id\":\"https://diyhistory.org/toyo/toyo3/iiif/2/ZJG048-2/annotation/p0006-image\",\"@type\":\"oa:Annotation\",\"motivation\":\"sc:painting\",\"resource\":{\"@id\":\"https://diyhistory.org/toyo/toyo3/iiif-img/2/5084/full/800,600/0/default.jpg\",\"@type\":\"dctypes:Image\",\"format\":\"image/jpeg\",\"width\":1440,\"height\":1080,\"service\":{\"@context\":\"http://iiif.io/api/image/2/context.json\",\"@id\":\"https://diyhistory.org/toyo/toyo3/iiif-img/2/5084\",\"profile\":\"http://iiif.io/api/image/2/level2.json\"}},\"on\":\"https://diyhistory.org/toyo/toyo3/iiif/2/ZJG048-2/canvas/p6\"}],\"metadata\":[{\"label\":\"Title\",\"value\":\"ZJG048\\u00d7200-2-3to2D\"},{\"label\":\"Extent\",\"value\":\"200\"}]},{\"@id\":\"https://diyhistory.org/toyo/toyo3/iiif/2/ZJG048-2/canvas/p7\",\"@type\":\"sc:Canvas\",\"label\":{\"type\":\"literal\",\"property_id\":1,\"property_label\":\"Title\",\"is_public\":true,\"@value\":\"ZJG048\\u00d7200-2\"},\"thumbnail\":{\"@id\":\"https://diyhistory.org/toyo/toyo3/files/medium/cad94e90a36a26a9d5e1fe528a47932b156200b0.jpg\",\"@type\":\"dctypes:Image\",\"format\":\"image/jpeg\",\"width\":200,\"height\":150},\"width\":1440,\"height\":1080,\"images\":[{\"@id\":\"https://diyhistory.org/toyo/toyo3/iiif/2/ZJG048-2/annotation/p0007-image\",\"@type\":\"oa:Annotation\",\"motivation\":\"sc:painting\",\"resource\":{\"@id\":\"https://diyhistory.org/toyo/toyo3/iiif-img/2/5085/full/800,600/0/default.jpg\",\"@type\":\"dctypes:Image\",\"format\":\"image/jpeg\",\"width\":1440,\"height\":1080,\"service\":{\"@context\":\"http://iiif.io/api/image/2/context.json\",\"@id\":\"https://diyhistory.org/toyo/toyo3/iiif-img/2/5085\",\"profile\":\"http://iiif.io/api/image/2/level2.json\"}},\"on\":\"https://diyhistory.org/toyo/toyo3/iiif/2/ZJG048-2/canvas/p7\"}],\"metadata\":[{\"label\":\"Title\",\"value\":\"ZJG048\\u00d7200-2\"},{\"label\":\"Extent\",\"value\":\"200\"}]},{\"@id\":\"https://diyhistory.org/toyo/toyo3/iiif/2/ZJG048-2/canvas/p8\",\"@type\":\"sc:Canvas\",\"label\":{\"type\":\"literal\",\"property_id\":1,\"property_label\":\"Title\",\"is_public\":true,\"@value\":\"ZJG048\\u00d7200-2compo\"},\"thumbnail\":{\"@id\":\"https://diyhistory.org/toyo/toyo3/files/medium/b64f889cb13555c9e29c8d4bfc2a7b26609a1713.jpg\",\"@type\":\"dctypes:Image\",\"format\":\"image/jpeg\",\"width\":200,\"height\":150},\"width\":1440,\"height\":1080,\"images\":[{\"@id\":\"https://diyhistory.org/toyo/toyo3/iiif/2/ZJG048-2/annotation/p0008-image\",\"@type\":\"oa:Annotation\",\"motivation\":\"sc:painting\",\"resource\":{\"@id\":\"https://diyhistory.org/toyo/toyo3/iiif-img/2/5086/full/800,600/0/default.jpg\",\"@type\":\"dctypes:Image\",\"format\":\"image/jpeg\",\"width\":1440,\"height\":1080,\"service\":{\"@context\":\"http://iiif.io/api/image/2/context.json\",\"@id\":\"https://diyhistory.org/toyo/toyo3/iiif-img/2/5086\",\"profile\":\"http://iiif.io/api/image/2/level2.json\"}},\"on\":\"https://diyhistory.org/toyo/toyo3/iiif/2/ZJG048-2/canvas/p8\"}],\"metadata\":[{\"label\":\"Title\",\"value\":\"ZJG048\\u00d7200-2compo\"},{\"label\":\"Extent\",\"value\":\"200\"}]},{\"@id\":\"https://diyhistory.org/toyo/toyo3/iiif/2/ZJG048-2/canvas/p9\",\"@type\":\"sc:Canvas\",\"label\":{\"type\":\"literal\",\"property_id\":1,\"property_label\":\"Title\",\"is_public\":true,\"@value\":\"ZJG048\\u00d7500-2-3D\"},\"thumbnail\":{\"@id\":\"https://diyhistory.org/toyo/toyo3/files/medium/baae3f25b5af50dd8caa8ecc0e093c2858f73992.jpg\",\"@type\":\"dctypes:Image\",\"format\":\"image/jpeg\",\"width\":200,\"height\":150},\"width\":1440,\"height\":1080,\"images\":[{\"@id\":\"https://diyhistory.org/toyo/toyo3/iiif/2/ZJG048-2/annotation/p0009-image\",\"@type\":\"oa:Annotation\",\"motivation\":\"sc:painting\",\"resource\":{\"@id\":\"https://diyhistory.org/toyo/toyo3/iiif-img/2/5087/full/800,600/0/default.jpg\",\"@type\":\"dctypes:Image\",\"format\":\"image/jpeg\",\"width\":1440,\"height\":1080,\"service\":{\"@context\":\"http://iiif.io/api/image/2/context.json\",\"@id\":\"https://diyhistory.org/toyo/toyo3/iiif-img/2/5087\",\"profile\":\"http://iiif.io/api/image/2/level2.json\"}},\"on\":\"https://diyhistory.org/toyo/toyo3/iiif/2/ZJG048-2/canvas/p9\"}],\"metadata\":[{\"label\":\"Title\",\"value\":\"ZJG048\\u00d7500-2-3D\"},{\"label\":\"Extent\",\"value\":\"500\"}]},{\"@id\":\"https://diyhistory.org/toyo/toyo3/iiif/2/ZJG048-2/canvas/p10\",\"@type\":\"sc:Canvas\",\"label\":{\"type\":\"literal\",\"property_id\":1,\"property_label\":\"Title\",\"is_public\":true,\"@value\":\"ZJG048\\u00d7500-2-3Dsca\"},\"thumbnail\":{\"@id\":\"https://diyhistory.org/toyo/toyo3/files/medium/d13077687a6054ae397e39215f4ceb021cdd4003.jpg\",\"@type\":\"dctypes:Image\",\"format\":\"image/jpeg\",\"width\":200,\"height\":150},\"width\":1440,\"height\":1080,\"images\":[{\"@id\":\"https://diyhistory.org/toyo/toyo3/iiif/2/ZJG048-2/annotation/p0010-image\",\"@type\":\"oa:Annotation\",\"motivation\":\"sc:painting\",\"resource\":{\"@id\":\"https://diyhistory.org/toyo/toyo3/iiif-img/2/5088/full/800,600/0/default.jpg\",\"@type\":\"dctypes:Image\",\"format\":\"image/jpeg\",\"width\":1440,\"height\":1080,\"service\":{\"@context\":\"http://iiif.io/api/image/2/context.json\",\"@id\":\"https://diyhistory.org/toyo/toyo3/iiif-img/2/5088\",\"profile\":\"http://iiif.io/api/image/2/level2.json\"}},\"on\":\"https://diyhistory.org/toyo/toyo3/iiif/2/ZJG048-2/canvas/p10\"}],\"metadata\":[{\"label\":\"Title\",\"value\":\"ZJG048\\u00d7500-2-3Dsca\"},{\"label\":\"Extent\",\"value\":\"500\"}]},{\"@id\":\"https://diyhistory.org/toyo/toyo3/iiif/2/ZJG048-2/canvas/p11\",\"@type\":\"sc:Canvas\",\"label\":{\"type\":\"literal\",\"property_id\":1,\"property_label\":\"Title\",\"is_public\":true,\"@value\":\"ZJG048\\u00d7500-2-3to2D\"},\"thumbnail\":{\"@id\":\"https://diyhistory.org/toyo/toyo3/files/medium/9459d8b9829297dd6f8625801e46f60e6acd2506.jpg\",\"@type\":\"dctypes:Image\",\"format\":\"image/jpeg\",\"width\":200,\"height\":150},\"width\":1440,\"height\":1080,\"images\":[{\"@id\":\"https://diyhistory.org/toyo/toyo3/iiif/2/ZJG048-2/annotation/p0011-image\",\"@type\":\"oa:Annotation\",\"motivation\":\"sc:painting\",\"resource\":{\"@id\":\"https://diyhistory.org/toyo/toyo3/iiif-img/2/5089/full/800,600/0/default.jpg\",\"@type\":\"dctypes:Image\",\"format\":\"image/jpeg\",\"width\":1440,\"height\":1080,\"service\":{\"@context\":\"http://iiif.io/api/image/2/context.json\",\"@id\":\"https://diyhistory.org/toyo/toyo3/iiif-img/2/5089\",\"profile\":\"http://iiif.io/api/image/2/level2.json\"}},\"on\":\"https://diyhistory.org/toyo/toyo3/iiif/2/ZJG048-2/canvas/p11\"}],\"metadata\":[{\"label\":\"Title\",\"value\":\"ZJG048\\u00d7500-2-3to2D\"},{\"label\":\"Extent\",\"value\":\"500\"}]},{\"@id\":\"https://diyhistory.org/toyo/toyo3/iiif/2/ZJG048-2/canvas/p12\",\"@type\":\"sc:Canvas\",\"label\":{\"type\":\"literal\",\"property_id\":1,\"property_label\":\"Title\",\"is_public\":true,\"@value\":\"ZJG048\\u00d7500-2\"},\"thumbnail\":{\"@id\":\"https://diyhistory.org/toyo/toyo3/files/medium/347d1170d571f95c35568e89690c58faff8f0f7d.jpg\",\"@type\":\"dctypes:Image\",\"format\":\"image/jpeg\",\"width\":200,\"height\":150},\"width\":1440,\"height\":1080,\"images\":[{\"@id\":\"https://diyhistory.org/toyo/toyo3/iiif/2/ZJG048-2/annotation/p0012-image\",\"@type\":\"oa:Annotation\",\"motivation\":\"sc:painting\",\"resource\":{\"@id\":\"https://diyhistory.org/toyo/toyo3/iiif-img/2/5090/full/800,600/0/default.jpg\",\"@type\":\"dctypes:Image\",\"format\":\"image/jpeg\",\"width\":1440,\"height\":1080,\"service\":{\"@context\":\"http://iiif.io/api/image/2/context.json\",\"@id\":\"https://diyhistory.org/toyo/toyo3/iiif-img/2/5090\",\"profile\":\"http://iiif.io/api/image/2/level2.json\"}},\"on\":\"https://diyhistory.org/toyo/toyo3/iiif/2/ZJG048-2/canvas/p12\"}],\"metadata\":[{\"label\":\"Title\",\"value\":\"ZJG048\\u00d7500-2\"},{\"label\":\"Extent\",\"value\":\"500\"}]},{\"@id\":\"https://diyhistory.org/toyo/toyo3/iiif/2/ZJG048-2/canvas/p13\",\"@type\":\"sc:Canvas\",\"label\":{\"type\":\"literal\",\"property_id\":1,\"property_label\":\"Title\",\"is_public\":true,\"@value\":\"ZJG048\\u00d7500-2compo\"},\"thumbnail\":{\"@id\":\"https://diyhistory.org/toyo/toyo3/files/medium/78927254b5c49c0bfec41a0b466d3b9f9505a6bc.jpg\",\"@type\":\"dctypes:Image\",\"format\":\"image/jpeg\",\"width\":200,\"height\":150},\"width\":1440,\"height\":1080,\"images\":[{\"@id\":\"https://diyhistory.org/toyo/toyo3/iiif/2/ZJG048-2/annotation/p0013-image\",\"@type\":\"oa:Annotation\",\"motivation\":\"sc:painting\",\"resource\":{\"@id\":\"https://diyhistory.org/toyo/toyo3/iiif-img/2/5091/full/800,600/0/default.jpg\",\"@type\":\"dctypes:Image\",\"format\":\"image/jpeg\",\"width\":1440,\"height\":1080,\"service\":{\"@context\":\"http://iiif.io/api/image/2/context.json\",\"@id\":\"https://diyhistory.org/toyo/toyo3/iiif-img/2/5091\",\"profile\":\"http://iiif.io/api/image/2/level2.json\"}},\"on\":\"https://diyhistory.org/toyo/toyo3/iiif/2/ZJG048-2/canvas/p13\"}],\"metadata\":[{\"label\":\"Title\",\"value\":\"ZJG048\\u00d7500-2compo\"},{\"label\":\"Extent\",\"value\":\"500\"}]},{\"@id\":\"https://diyhistory.org/toyo/toyo3/iiif/2/ZJG048-2/canvas/p14\",\"@type\":\"sc:Canvas\",\"label\":{\"type\":\"literal\",\"property_id\":1,\"property_label\":\"Title\",\"is_public\":true,\"@value\":\"ZJG048\\u00d71000-2-3D\"},\"thumbnail\":{\"@id\":\"https://diyhistory.org/toyo/toyo3/files/medium/94297a189b626d5bfd6cab18f954e266a55911aa.jpg\",\"@type\":\"dctypes:Image\",\"format\":\"image/jpeg\",\"width\":200,\"height\":150},\"width\":1440,\"height\":1080,\"images\":[{\"@id\":\"https://diyhistory.org/toyo/toyo3/iiif/2/ZJG048-2/annotation/p0014-image\",\"@type\":\"oa:Annotation\",\"motivation\":\"sc:painting\",\"resource\":{\"@id\":\"https://diyhistory.org/toyo/toyo3/iiif-img/2/5092/full/800,600/0/default.jpg\",\"@type\":\"dctypes:Image\",\"format\":\"image/jpeg\",\"width\":1440,\"height\":1080,\"service\":{\"@context\":\"http://iiif.io/api/image/2/context.json\",\"@id\":\"https://diyhistory.org/toyo/toyo3/iiif-img/2/5092\",\"profile\":\"http://iiif.io/api/image/2/level2.json\"}},\"on\":\"https://diyhistory.org/toyo/toyo3/iiif/2/ZJG048-2/canvas/p14\"}],\"metadata\":[{\"label\":\"Title\",\"value\":\"ZJG048\\u00d71000-2-3D\"},{\"label\":\"Extent\",\"value\":\"1000\"}]},{\"@id\":\"https://diyhistory.org/toyo/toyo3/iiif/2/ZJG048-2/canvas/p15\",\"@type\":\"sc:Canvas\",\"label\":{\"type\":\"literal\",\"property_id\":1,\"property_label\":\"Title\",\"is_public\":true,\"@value\":\"ZJG048\\u00d71000-2-3Dsca\"},\"thumbnail\":{\"@id\":\"https://diyhistory.org/toyo/toyo3/files/medium/7dbcae47615dcba603cc341c7ecaad7d66326e78.jpg\",\"@type\":\"dctypes:Image\",\"format\":\"image/jpeg\",\"width\":200,\"height\":150},\"width\":1440,\"height\":1080,\"images\":[{\"@id\":\"https://diyhistory.org/toyo/toyo3/iiif/2/ZJG048-2/annotation/p0015-image\",\"@type\":\"oa:Annotation\",\"motivation\":\"sc:painting\",\"resource\":{\"@id\":\"https://diyhistory.org/toyo/toyo3/iiif-img/2/5093/full/800,600/0/default.jpg\",\"@type\":\"dctypes:Image\",\"format\":\"image/jpeg\",\"width\":1440,\"height\":1080,\"service\":{\"@context\":\"http://iiif.io/api/image/2/context.json\",\"@id\":\"https://diyhistory.org/toyo/toyo3/iiif-img/2/5093\",\"profile\":\"http://iiif.io/api/image/2/level2.json\"}},\"on\":\"https://diyhistory.org/toyo/toyo3/iiif/2/ZJG048-2/canvas/p15\"}],\"metadata\":[{\"label\":\"Title\",\"value\":\"ZJG048\\u00d71000-2-3Dsca\"},{\"label\":\"Extent\",\"value\":\"1000\"}]},{\"@id\":\"https://diyhistory.org/toyo/toyo3/iiif/2/ZJG048-2/canvas/p16\",\"@type\":\"sc:Canvas\",\"label\":{\"type\":\"literal\",\"property_id\":1,\"property_label\":\"Title\",\"is_public\":true,\"@value\":\"ZJG048\\u00d71000-2-3to2D\"},\"thumbnail\":{\"@id\":\"https://diyhistory.org/toyo/toyo3/files/medium/17a3856ac113797631b625137b6e67c60c7bb406.jpg\",\"@type\":\"dctypes:Image\",\"format\":\"image/jpeg\",\"width\":200,\"height\":150},\"width\":1440,\"height\":1080,\"images\":[{\"@id\":\"https://diyhistory.org/toyo/toyo3/iiif/2/ZJG048-2/annotation/p0016-image\",\"@type\":\"oa:Annotation\",\"motivation\":\"sc:painting\",\"resource\":{\"@id\":\"https://diyhistory.org/toyo/toyo3/iiif-img/2/5094/full/800,600/0/default.jpg\",\"@type\":\"dctypes:Image\",\"format\":\"image/jpeg\",\"width\":1440,\"height\":1080,\"service\":{\"@context\":\"http://iiif.io/api/image/2/context.json\",\"@id\":\"https://diyhistory.org/toyo/toyo3/iiif-img/2/5094\",\"profile\":\"http://iiif.io/api/image/2/level2.json\"}},\"on\":\"https://diyhistory.org/toyo/toyo3/iiif/2/ZJG048-2/canvas/p16\"}],\"metadata\":[{\"label\":\"Title\",\"value\":\"ZJG048\\u00d71000-2-3to2D\"},{\"label\":\"Extent\",\"value\":\"1000\"}]},{\"@id\":\"https://diyhistory.org/toyo/toyo3/iiif/2/ZJG048-2/canvas/p17\",\"@type\":\"sc:Canvas\",\"label\":{\"type\":\"literal\",\"property_id\":1,\"property_label\":\"Title\",\"is_public\":true,\"@value\":\"ZJG048\\u00d71000-2\"},\"thumbnail\":{\"@id\":\"https://diyhistory.org/toyo/toyo3/files/medium/acba12ce975f334045a8e07b7eadb33c0dab5489.jpg\",\"@type\":\"dctypes:Image\",\"format\":\"image/jpeg\",\"width\":200,\"height\":150},\"width\":1440,\"height\":1080,\"images\":[{\"@id\":\"https://diyhistory.org/toyo/toyo3/iiif/2/ZJG048-2/annotation/p0017-image\",\"@type\":\"oa:Annotation\",\"motivation\":\"sc:painting\",\"resource\":{\"@id\":\"https://diyhistory.org/toyo/toyo3/iiif-img/2/5095/full/800,600/0/default.jpg\",\"@type\":\"dctypes:Image\",\"format\":\"image/jpeg\",\"width\":1440,\"height\":1080,\"service\":{\"@context\":\"http://iiif.io/api/image/2/context.json\",\"@id\":\"https://diyhistory.org/toyo/toyo3/iiif-img/2/5095\",\"profile\":\"http://iiif.io/api/image/2/level2.json\"}},\"on\":\"https://diyhistory.org/toyo/toyo3/iiif/2/ZJG048-2/canvas/p17\"}],\"metadata\":[{\"label\":\"Title\",\"value\":\"ZJG048\\u00d71000-2\"},{\"label\":\"Extent\",\"value\":\"1000\"}]},{\"@id\":\"https://diyhistory.org/toyo/toyo3/iiif/2/ZJG048-2/canvas/p18\",\"@type\":\"sc:Canvas\",\"label\":{\"type\":\"literal\",\"property_id\":1,\"property_label\":\"Title\",\"is_public\":true,\"@value\":\"ZJG048\\u00d71000-2compo\"},\"thumbnail\":{\"@id\":\"https://diyhistory.org/toyo/toyo3/files/medium/4661c7c5d415e8ce759a9f10ed7e7b7202345f02.jpg\",\"@type\":\"dctypes:Image\",\"format\":\"image/jpeg\",\"width\":200,\"height\":150},\"width\":1440,\"height\":1080,\"images\":[{\"@id\":\"https://diyhistory.org/toyo/toyo3/iiif/2/ZJG048-2/annotation/p0018-image\",\"@type\":\"oa:Annotation\",\"motivation\":\"sc:painting\",\"resource\":{\"@id\":\"https://diyhistory.org/toyo/toyo3/iiif-img/2/5096/full/800,600/0/default.jpg\",\"@type\":\"dctypes:Image\",\"format\":\"image/jpeg\",\"width\":1440,\"height\":1080,\"service\":{\"@context\":\"http://iiif.io/api/image/2/context.json\",\"@id\":\"https://diyhistory.org/toyo/toyo3/iiif-img/2/5096\",\"profile\":\"http://iiif.io/api/image/2/level2.json\"}},\"on\":\"https://diyhistory.org/toyo/toyo3/iiif/2/ZJG048-2/canvas/p18\"}],\"metadata\":[{\"label\":\"Title\",\"value\":\"ZJG048\\u00d71000-2compo\"},{\"label\":\"Extent\",\"value\":\"1000\"}]}]}]}"
        },
        {
            "element": {
                "id": 58,
                "name": "IIIF Type",
                "resource": "elements",
                "url": "https://diyhistory.org/toyo/omekac3/api/elements/58"
            },
            "element_set": {
                "id": 6,
                "name": "IIIF Collection Metadata",
                "resource": "element_sets",
                "url": "https://diyhistory.org/toyo/omekac3/api/element_sets/6"
            },
            "html": false,
            "text": "Manifest"
        },
        {
            "element": {
                "id": 59,
                "name": "Parent Collection",
                "resource": "elements",
                "url": "https://diyhistory.org/toyo/omekac3/api/elements/59"
            },
            "element_set": {
                "id": 6,
                "name": "IIIF Collection Metadata",
                "resource": "element_sets",
                "url": "https://diyhistory.org/toyo/omekac3/api/element_sets/6"
            },
            "html": false,
            "text": "d7884de6-5890-4002-967b-25f599af04bb"
        },
        {
            "element": {
                "id": 61,
                "name": "UUID",
                "resource": "elements",
                "url": "https://diyhistory.org/toyo/omekac3/api/elements/61"
            },
            "element_set": {
                "id": 6,
                "name": "IIIF Collection Metadata",
                "resource": "element_sets",
                "url": "https://diyhistory.org/toyo/omekac3/api/element_sets/6"
            },
            "html": false,
            "text": "51ac71f3-63f7-42a7-b84b-e13f0b44a0dd"
        }
    ],
    "extended_resources": [],
    "featured": false,
    "id": 298,
    "items": {
        "count": 18,
        "resource": "items",
        "url": "https://diyhistory.org/toyo/omekac3/api/items?collection=298"
    },
    "modified": "2021-02-10T14:05:05+00:00",
    "owner": {
        "id": 1,
        "resource": "users",
        "url": "https://diyhistory.org/toyo/omekac3/api/users/1"
    },
    "public": false,
    "url": "https://diyhistory.org/toyo/omekac3/api/collections/298"
}