{
    "@id": "https://diyhistory.org/toyo/omekac3/api/324.json",
    "added": "2021-02-10T14:05:14+00:00",
    "element_texts": [
        {
            "element": {
                "id": 50,
                "name": "Title",
                "resource": "elements",
                "url": "https://diyhistory.org/toyo/omekac3/api/elements/50"
            },
            "element_set": {
                "id": 1,
                "name": "Dublin Core",
                "resource": "element_sets",
                "url": "https://diyhistory.org/toyo/omekac3/api/element_sets/1"
            },
            "html": false,
            "text": "ZKG053毛竹生料混料 観察ポイント3"
        },
        {
            "element": {
                "id": 48,
                "name": "Source",
                "resource": "elements",
                "url": "https://diyhistory.org/toyo/omekac3/api/elements/48"
            },
            "element_set": {
                "id": 1,
                "name": "Dublin Core",
                "resource": "element_sets",
                "url": "https://diyhistory.org/toyo/omekac3/api/element_sets/1"
            },
            "html": false,
            "text": "https://diyhistory.org/toyo/toyo3/iiif/2/ZKG053-3/manifest"
        },
        {
            "element": {
                "id": 45,
                "name": "Publisher",
                "resource": "elements",
                "url": "https://diyhistory.org/toyo/omekac3/api/elements/45"
            },
            "element_set": {
                "id": 1,
                "name": "Dublin Core",
                "resource": "element_sets",
                "url": "https://diyhistory.org/toyo/omekac3/api/element_sets/1"
            },
            "html": false,
            "text": "Provided by Example Organization"
        },
        {
            "element": {
                "id": 57,
                "name": "Original @id",
                "resource": "elements",
                "url": "https://diyhistory.org/toyo/omekac3/api/elements/57"
            },
            "element_set": {
                "id": 6,
                "name": "IIIF Collection Metadata",
                "resource": "element_sets",
                "url": "https://diyhistory.org/toyo/omekac3/api/element_sets/6"
            },
            "html": false,
            "text": "https://diyhistory.org/toyo/toyo3/iiif/2/ZKG053-3/manifest"
        },
        {
            "element": {
                "id": 60,
                "name": "JSON Data",
                "resource": "elements",
                "url": "https://diyhistory.org/toyo/omekac3/api/elements/60"
            },
            "element_set": {
                "id": 6,
                "name": "IIIF Collection Metadata",
                "resource": "element_sets",
                "url": "https://diyhistory.org/toyo/omekac3/api/element_sets/6"
            },
            "html": false,
            "text": "{\"@context\":\"http://iiif.io/api/presentation/2/context.json\",\"@id\":\"https://diyhistory.org/toyo/toyo3/iiif/2/ZKG053-3/manifest\",\"@type\":\"sc:Manifest\",\"label\":\"ZKG053\\u6bdb\\u7af9\\u751f\\u6599\\u6df7\\u6599 \\u89b3\\u5bdf\\u30dd\\u30a4\\u30f3\\u30c83\",\"thumbnail\":{\"@id\":\"https://diyhistory.org/toyo/toyo3/files/medium/c55cf85ce89d8cb945e97acf9a075d442e6b2f4d.jpg\",\"@type\":\"dctypes:Image\",\"format\":\"image/jpeg\",\"width\":200,\"height\":150},\"attribution\":\"Provided by Example Organization\",\"related\":{\"@id\":\"https://diyhistory.org/toyo/toyo3\",\"format\":\"text/html\"},\"seeAlso\":{\"@id\":\"https://diyhistory.org/toyo/toyo3/api/items/403\",\"format\":\"application/ld+json\"},\"metadata\":[{\"label\":\"Title\",\"value\":\"ZKG053\\u6bdb\\u7af9\\u751f\\u6599\\u6df7\\u6599 \\u89b3\\u5bdf\\u30dd\\u30a4\\u30f3\\u30c83\"},{\"label\":\"Identifier\",\"value\":[\"ZKG053-3\",\"ZKG053-3\"]},{\"label\":\"Relation\",\"value\":\"<a class=\\\"resource-link\\\" href=\\\"https://diyhistory.org/toyo/toyo3\\\"><span class=\\\"resource-name\\\">ZKG053\\u6bdb\\u7af9\\u751f\\u6599\\u6df7\\u6599</span></a>\"}],\"sequences\":[{\"@id\":\"https://diyhistory.org/toyo/toyo3/iiif/2/ZKG053-3/sequence/normal\",\"@type\":\"sc:Sequence\",\"label\":\"Current Page Order\",\"viewingDirection\":\"left-to-right\",\"canvases\":[{\"@id\":\"https://diyhistory.org/toyo/toyo3/iiif/2/ZKG053-3/canvas/p1\",\"@type\":\"sc:Canvas\",\"label\":{\"type\":\"literal\",\"property_id\":1,\"property_label\":\"Title\",\"is_public\":true,\"@value\":\"ZKG053\\u00d720-3\"},\"thumbnail\":{\"@id\":\"https://diyhistory.org/toyo/toyo3/files/medium/c55cf85ce89d8cb945e97acf9a075d442e6b2f4d.jpg\",\"@type\":\"dctypes:Image\",\"format\":\"image/jpeg\",\"width\":200,\"height\":150},\"width\":1440,\"height\":1080,\"images\":[{\"@id\":\"https://diyhistory.org/toyo/toyo3/iiif/2/ZKG053-3/annotation/p0001-image\",\"@type\":\"oa:Annotation\",\"motivation\":\"sc:painting\",\"resource\":{\"@id\":\"https://diyhistory.org/toyo/toyo3/iiif-img/2/5547/full/800,600/0/default.jpg\",\"@type\":\"dctypes:Image\",\"format\":\"image/jpeg\",\"width\":1440,\"height\":1080,\"service\":{\"@context\":\"http://iiif.io/api/image/2/context.json\",\"@id\":\"https://diyhistory.org/toyo/toyo3/iiif-img/2/5547\",\"profile\":\"http://iiif.io/api/image/2/level2.json\"}},\"on\":\"https://diyhistory.org/toyo/toyo3/iiif/2/ZKG053-3/canvas/p1\"}],\"metadata\":[{\"label\":\"Title\",\"value\":\"ZKG053\\u00d720-3\"},{\"label\":\"Extent\",\"value\":\"20\"}]},{\"@id\":\"https://diyhistory.org/toyo/toyo3/iiif/2/ZKG053-3/canvas/p2\",\"@type\":\"sc:Canvas\",\"label\":{\"type\":\"literal\",\"property_id\":1,\"property_label\":\"Title\",\"is_public\":true,\"@value\":\"ZKG053\\u00d750-3\"},\"thumbnail\":{\"@id\":\"https://diyhistory.org/toyo/toyo3/files/medium/f4ef908d1970e231135340c741ed4bd8dc0925c0.jpg\",\"@type\":\"dctypes:Image\",\"format\":\"image/jpeg\",\"width\":200,\"height\":150},\"width\":1440,\"height\":1080,\"images\":[{\"@id\":\"https://diyhistory.org/toyo/toyo3/iiif/2/ZKG053-3/annotation/p0002-image\",\"@type\":\"oa:Annotation\",\"motivation\":\"sc:painting\",\"resource\":{\"@id\":\"https://diyhistory.org/toyo/toyo3/iiif-img/2/5548/full/800,600/0/default.jpg\",\"@type\":\"dctypes:Image\",\"format\":\"image/jpeg\",\"width\":1440,\"height\":1080,\"service\":{\"@context\":\"http://iiif.io/api/image/2/context.json\",\"@id\":\"https://diyhistory.org/toyo/toyo3/iiif-img/2/5548\",\"profile\":\"http://iiif.io/api/image/2/level2.json\"}},\"on\":\"https://diyhistory.org/toyo/toyo3/iiif/2/ZKG053-3/canvas/p2\"}],\"metadata\":[{\"label\":\"Title\",\"value\":\"ZKG053\\u00d750-3\"},{\"label\":\"Extent\",\"value\":\"50\"}]},{\"@id\":\"https://diyhistory.org/toyo/toyo3/iiif/2/ZKG053-3/canvas/p3\",\"@type\":\"sc:Canvas\",\"label\":{\"type\":\"literal\",\"property_id\":1,\"property_label\":\"Title\",\"is_public\":true,\"@value\":\"ZKG053\\u00d7100-3\"},\"thumbnail\":{\"@id\":\"https://diyhistory.org/toyo/toyo3/files/medium/be15c796ccec9f434f3016de52c042bd92ec50fd.jpg\",\"@type\":\"dctypes:Image\",\"format\":\"image/jpeg\",\"width\":200,\"height\":150},\"width\":1440,\"height\":1080,\"images\":[{\"@id\":\"https://diyhistory.org/toyo/toyo3/iiif/2/ZKG053-3/annotation/p0003-image\",\"@type\":\"oa:Annotation\",\"motivation\":\"sc:painting\",\"resource\":{\"@id\":\"https://diyhistory.org/toyo/toyo3/iiif-img/2/5549/full/800,600/0/default.jpg\",\"@type\":\"dctypes:Image\",\"format\":\"image/jpeg\",\"width\":1440,\"height\":1080,\"service\":{\"@context\":\"http://iiif.io/api/image/2/context.json\",\"@id\":\"https://diyhistory.org/toyo/toyo3/iiif-img/2/5549\",\"profile\":\"http://iiif.io/api/image/2/level2.json\"}},\"on\":\"https://diyhistory.org/toyo/toyo3/iiif/2/ZKG053-3/canvas/p3\"}],\"metadata\":[{\"label\":\"Title\",\"value\":\"ZKG053\\u00d7100-3\"},{\"label\":\"Extent\",\"value\":\"100\"}]},{\"@id\":\"https://diyhistory.org/toyo/toyo3/iiif/2/ZKG053-3/canvas/p4\",\"@type\":\"sc:Canvas\",\"label\":{\"type\":\"literal\",\"property_id\":1,\"property_label\":\"Title\",\"is_public\":true,\"@value\":\"ZKG053\\u00d7200-3-3D\"},\"thumbnail\":{\"@id\":\"https://diyhistory.org/toyo/toyo3/files/medium/c052c99701e92015067ef93cad2a3fde7e8fd0c4.jpg\",\"@type\":\"dctypes:Image\",\"format\":\"image/jpeg\",\"width\":200,\"height\":150},\"width\":1440,\"height\":1080,\"images\":[{\"@id\":\"https://diyhistory.org/toyo/toyo3/iiif/2/ZKG053-3/annotation/p0004-image\",\"@type\":\"oa:Annotation\",\"motivation\":\"sc:painting\",\"resource\":{\"@id\":\"https://diyhistory.org/toyo/toyo3/iiif-img/2/5550/full/800,600/0/default.jpg\",\"@type\":\"dctypes:Image\",\"format\":\"image/jpeg\",\"width\":1440,\"height\":1080,\"service\":{\"@context\":\"http://iiif.io/api/image/2/context.json\",\"@id\":\"https://diyhistory.org/toyo/toyo3/iiif-img/2/5550\",\"profile\":\"http://iiif.io/api/image/2/level2.json\"}},\"on\":\"https://diyhistory.org/toyo/toyo3/iiif/2/ZKG053-3/canvas/p4\"}],\"metadata\":[{\"label\":\"Title\",\"value\":\"ZKG053\\u00d7200-3-3D\"},{\"label\":\"Extent\",\"value\":\"200\"}]},{\"@id\":\"https://diyhistory.org/toyo/toyo3/iiif/2/ZKG053-3/canvas/p5\",\"@type\":\"sc:Canvas\",\"label\":{\"type\":\"literal\",\"property_id\":1,\"property_label\":\"Title\",\"is_public\":true,\"@value\":\"ZKG053\\u00d7200-3-3Dsca\"},\"thumbnail\":{\"@id\":\"https://diyhistory.org/toyo/toyo3/files/medium/4ec69c9ded9449fe0a4efeb7d92f001c6028416d.jpg\",\"@type\":\"dctypes:Image\",\"format\":\"image/jpeg\",\"width\":200,\"height\":150},\"width\":1440,\"height\":1080,\"images\":[{\"@id\":\"https://diyhistory.org/toyo/toyo3/iiif/2/ZKG053-3/annotation/p0005-image\",\"@type\":\"oa:Annotation\",\"motivation\":\"sc:painting\",\"resource\":{\"@id\":\"https://diyhistory.org/toyo/toyo3/iiif-img/2/5551/full/800,600/0/default.jpg\",\"@type\":\"dctypes:Image\",\"format\":\"image/jpeg\",\"width\":1440,\"height\":1080,\"service\":{\"@context\":\"http://iiif.io/api/image/2/context.json\",\"@id\":\"https://diyhistory.org/toyo/toyo3/iiif-img/2/5551\",\"profile\":\"http://iiif.io/api/image/2/level2.json\"}},\"on\":\"https://diyhistory.org/toyo/toyo3/iiif/2/ZKG053-3/canvas/p5\"}],\"metadata\":[{\"label\":\"Title\",\"value\":\"ZKG053\\u00d7200-3-3Dsca\"},{\"label\":\"Extent\",\"value\":\"200\"}]},{\"@id\":\"https://diyhistory.org/toyo/toyo3/iiif/2/ZKG053-3/canvas/p6\",\"@type\":\"sc:Canvas\",\"label\":{\"type\":\"literal\",\"property_id\":1,\"property_label\":\"Title\",\"is_public\":true,\"@value\":\"ZKG053\\u00d7200-3-3to2D\"},\"thumbnail\":{\"@id\":\"https://diyhistory.org/toyo/toyo3/files/medium/89b9e1966ec0b3181cbbb2f070dd384dac70e657.jpg\",\"@type\":\"dctypes:Image\",\"format\":\"image/jpeg\",\"width\":200,\"height\":150},\"width\":1440,\"height\":1080,\"images\":[{\"@id\":\"https://diyhistory.org/toyo/toyo3/iiif/2/ZKG053-3/annotation/p0006-image\",\"@type\":\"oa:Annotation\",\"motivation\":\"sc:painting\",\"resource\":{\"@id\":\"https://diyhistory.org/toyo/toyo3/iiif-img/2/5552/full/800,600/0/default.jpg\",\"@type\":\"dctypes:Image\",\"format\":\"image/jpeg\",\"width\":1440,\"height\":1080,\"service\":{\"@context\":\"http://iiif.io/api/image/2/context.json\",\"@id\":\"https://diyhistory.org/toyo/toyo3/iiif-img/2/5552\",\"profile\":\"http://iiif.io/api/image/2/level2.json\"}},\"on\":\"https://diyhistory.org/toyo/toyo3/iiif/2/ZKG053-3/canvas/p6\"}],\"metadata\":[{\"label\":\"Title\",\"value\":\"ZKG053\\u00d7200-3-3to2D\"},{\"label\":\"Extent\",\"value\":\"200\"}]},{\"@id\":\"https://diyhistory.org/toyo/toyo3/iiif/2/ZKG053-3/canvas/p7\",\"@type\":\"sc:Canvas\",\"label\":{\"type\":\"literal\",\"property_id\":1,\"property_label\":\"Title\",\"is_public\":true,\"@value\":\"ZKG053\\u00d7200-3\"},\"thumbnail\":{\"@id\":\"https://diyhistory.org/toyo/toyo3/files/medium/4d64bf741b1902865220e1e4294f3ccd079bef62.jpg\",\"@type\":\"dctypes:Image\",\"format\":\"image/jpeg\",\"width\":200,\"height\":150},\"width\":1440,\"height\":1080,\"images\":[{\"@id\":\"https://diyhistory.org/toyo/toyo3/iiif/2/ZKG053-3/annotation/p0007-image\",\"@type\":\"oa:Annotation\",\"motivation\":\"sc:painting\",\"resource\":{\"@id\":\"https://diyhistory.org/toyo/toyo3/iiif-img/2/5553/full/800,600/0/default.jpg\",\"@type\":\"dctypes:Image\",\"format\":\"image/jpeg\",\"width\":1440,\"height\":1080,\"service\":{\"@context\":\"http://iiif.io/api/image/2/context.json\",\"@id\":\"https://diyhistory.org/toyo/toyo3/iiif-img/2/5553\",\"profile\":\"http://iiif.io/api/image/2/level2.json\"}},\"on\":\"https://diyhistory.org/toyo/toyo3/iiif/2/ZKG053-3/canvas/p7\"}],\"metadata\":[{\"label\":\"Title\",\"value\":\"ZKG053\\u00d7200-3\"},{\"label\":\"Extent\",\"value\":\"200\"}]},{\"@id\":\"https://diyhistory.org/toyo/toyo3/iiif/2/ZKG053-3/canvas/p8\",\"@type\":\"sc:Canvas\",\"label\":{\"type\":\"literal\",\"property_id\":1,\"property_label\":\"Title\",\"is_public\":true,\"@value\":\"ZKG053\\u00d7200-3compo\"},\"thumbnail\":{\"@id\":\"https://diyhistory.org/toyo/toyo3/files/medium/16affaaf9273010b87e55779b625fa0207a9bd7b.jpg\",\"@type\":\"dctypes:Image\",\"format\":\"image/jpeg\",\"width\":200,\"height\":150},\"width\":1440,\"height\":1080,\"images\":[{\"@id\":\"https://diyhistory.org/toyo/toyo3/iiif/2/ZKG053-3/annotation/p0008-image\",\"@type\":\"oa:Annotation\",\"motivation\":\"sc:painting\",\"resource\":{\"@id\":\"https://diyhistory.org/toyo/toyo3/iiif-img/2/5554/full/800,600/0/default.jpg\",\"@type\":\"dctypes:Image\",\"format\":\"image/jpeg\",\"width\":1440,\"height\":1080,\"service\":{\"@context\":\"http://iiif.io/api/image/2/context.json\",\"@id\":\"https://diyhistory.org/toyo/toyo3/iiif-img/2/5554\",\"profile\":\"http://iiif.io/api/image/2/level2.json\"}},\"on\":\"https://diyhistory.org/toyo/toyo3/iiif/2/ZKG053-3/canvas/p8\"}],\"metadata\":[{\"label\":\"Title\",\"value\":\"ZKG053\\u00d7200-3compo\"},{\"label\":\"Extent\",\"value\":\"200\"}]},{\"@id\":\"https://diyhistory.org/toyo/toyo3/iiif/2/ZKG053-3/canvas/p9\",\"@type\":\"sc:Canvas\",\"label\":{\"type\":\"literal\",\"property_id\":1,\"property_label\":\"Title\",\"is_public\":true,\"@value\":\"ZKG053\\u00d7500-3-3D\"},\"thumbnail\":{\"@id\":\"https://diyhistory.org/toyo/toyo3/files/medium/da2f9bdd6a2e792646f4a8bd9c7f5a7aa2a62805.jpg\",\"@type\":\"dctypes:Image\",\"format\":\"image/jpeg\",\"width\":200,\"height\":150},\"width\":1440,\"height\":1080,\"images\":[{\"@id\":\"https://diyhistory.org/toyo/toyo3/iiif/2/ZKG053-3/annotation/p0009-image\",\"@type\":\"oa:Annotation\",\"motivation\":\"sc:painting\",\"resource\":{\"@id\":\"https://diyhistory.org/toyo/toyo3/iiif-img/2/5555/full/800,600/0/default.jpg\",\"@type\":\"dctypes:Image\",\"format\":\"image/jpeg\",\"width\":1440,\"height\":1080,\"service\":{\"@context\":\"http://iiif.io/api/image/2/context.json\",\"@id\":\"https://diyhistory.org/toyo/toyo3/iiif-img/2/5555\",\"profile\":\"http://iiif.io/api/image/2/level2.json\"}},\"on\":\"https://diyhistory.org/toyo/toyo3/iiif/2/ZKG053-3/canvas/p9\"}],\"metadata\":[{\"label\":\"Title\",\"value\":\"ZKG053\\u00d7500-3-3D\"},{\"label\":\"Extent\",\"value\":\"500\"}]},{\"@id\":\"https://diyhistory.org/toyo/toyo3/iiif/2/ZKG053-3/canvas/p10\",\"@type\":\"sc:Canvas\",\"label\":{\"type\":\"literal\",\"property_id\":1,\"property_label\":\"Title\",\"is_public\":true,\"@value\":\"ZKG053\\u00d7500-3-3Dsca\"},\"thumbnail\":{\"@id\":\"https://diyhistory.org/toyo/toyo3/files/medium/6605ee10268572a9a5deb181b98384ddf709bc96.jpg\",\"@type\":\"dctypes:Image\",\"format\":\"image/jpeg\",\"width\":200,\"height\":150},\"width\":1440,\"height\":1080,\"images\":[{\"@id\":\"https://diyhistory.org/toyo/toyo3/iiif/2/ZKG053-3/annotation/p0010-image\",\"@type\":\"oa:Annotation\",\"motivation\":\"sc:painting\",\"resource\":{\"@id\":\"https://diyhistory.org/toyo/toyo3/iiif-img/2/5556/full/800,600/0/default.jpg\",\"@type\":\"dctypes:Image\",\"format\":\"image/jpeg\",\"width\":1440,\"height\":1080,\"service\":{\"@context\":\"http://iiif.io/api/image/2/context.json\",\"@id\":\"https://diyhistory.org/toyo/toyo3/iiif-img/2/5556\",\"profile\":\"http://iiif.io/api/image/2/level2.json\"}},\"on\":\"https://diyhistory.org/toyo/toyo3/iiif/2/ZKG053-3/canvas/p10\"}],\"metadata\":[{\"label\":\"Title\",\"value\":\"ZKG053\\u00d7500-3-3Dsca\"},{\"label\":\"Extent\",\"value\":\"500\"}]},{\"@id\":\"https://diyhistory.org/toyo/toyo3/iiif/2/ZKG053-3/canvas/p11\",\"@type\":\"sc:Canvas\",\"label\":{\"type\":\"literal\",\"property_id\":1,\"property_label\":\"Title\",\"is_public\":true,\"@value\":\"ZKG053\\u00d7500-3-3to2D\"},\"thumbnail\":{\"@id\":\"https://diyhistory.org/toyo/toyo3/files/medium/8a3bc1a285230a203fbb6c2f6f9143411380ac26.jpg\",\"@type\":\"dctypes:Image\",\"format\":\"image/jpeg\",\"width\":200,\"height\":150},\"width\":1440,\"height\":1080,\"images\":[{\"@id\":\"https://diyhistory.org/toyo/toyo3/iiif/2/ZKG053-3/annotation/p0011-image\",\"@type\":\"oa:Annotation\",\"motivation\":\"sc:painting\",\"resource\":{\"@id\":\"https://diyhistory.org/toyo/toyo3/iiif-img/2/5557/full/800,600/0/default.jpg\",\"@type\":\"dctypes:Image\",\"format\":\"image/jpeg\",\"width\":1440,\"height\":1080,\"service\":{\"@context\":\"http://iiif.io/api/image/2/context.json\",\"@id\":\"https://diyhistory.org/toyo/toyo3/iiif-img/2/5557\",\"profile\":\"http://iiif.io/api/image/2/level2.json\"}},\"on\":\"https://diyhistory.org/toyo/toyo3/iiif/2/ZKG053-3/canvas/p11\"}],\"metadata\":[{\"label\":\"Title\",\"value\":\"ZKG053\\u00d7500-3-3to2D\"},{\"label\":\"Extent\",\"value\":\"500\"}]},{\"@id\":\"https://diyhistory.org/toyo/toyo3/iiif/2/ZKG053-3/canvas/p12\",\"@type\":\"sc:Canvas\",\"label\":{\"type\":\"literal\",\"property_id\":1,\"property_label\":\"Title\",\"is_public\":true,\"@value\":\"ZKG053\\u00d7500-3\"},\"thumbnail\":{\"@id\":\"https://diyhistory.org/toyo/toyo3/files/medium/a3e3d52032c47e3b42ede8bcc9ad43001608a0df.jpg\",\"@type\":\"dctypes:Image\",\"format\":\"image/jpeg\",\"width\":200,\"height\":150},\"width\":1440,\"height\":1080,\"images\":[{\"@id\":\"https://diyhistory.org/toyo/toyo3/iiif/2/ZKG053-3/annotation/p0012-image\",\"@type\":\"oa:Annotation\",\"motivation\":\"sc:painting\",\"resource\":{\"@id\":\"https://diyhistory.org/toyo/toyo3/iiif-img/2/5558/full/800,600/0/default.jpg\",\"@type\":\"dctypes:Image\",\"format\":\"image/jpeg\",\"width\":1440,\"height\":1080,\"service\":{\"@context\":\"http://iiif.io/api/image/2/context.json\",\"@id\":\"https://diyhistory.org/toyo/toyo3/iiif-img/2/5558\",\"profile\":\"http://iiif.io/api/image/2/level2.json\"}},\"on\":\"https://diyhistory.org/toyo/toyo3/iiif/2/ZKG053-3/canvas/p12\"}],\"metadata\":[{\"label\":\"Title\",\"value\":\"ZKG053\\u00d7500-3\"},{\"label\":\"Extent\",\"value\":\"500\"}]},{\"@id\":\"https://diyhistory.org/toyo/toyo3/iiif/2/ZKG053-3/canvas/p13\",\"@type\":\"sc:Canvas\",\"label\":{\"type\":\"literal\",\"property_id\":1,\"property_label\":\"Title\",\"is_public\":true,\"@value\":\"ZKG053\\u00d7500-3compo\"},\"thumbnail\":{\"@id\":\"https://diyhistory.org/toyo/toyo3/files/medium/619982360951137adf7d1615874fb5010dc69883.jpg\",\"@type\":\"dctypes:Image\",\"format\":\"image/jpeg\",\"width\":200,\"height\":150},\"width\":1440,\"height\":1080,\"images\":[{\"@id\":\"https://diyhistory.org/toyo/toyo3/iiif/2/ZKG053-3/annotation/p0013-image\",\"@type\":\"oa:Annotation\",\"motivation\":\"sc:painting\",\"resource\":{\"@id\":\"https://diyhistory.org/toyo/toyo3/iiif-img/2/5559/full/800,600/0/default.jpg\",\"@type\":\"dctypes:Image\",\"format\":\"image/jpeg\",\"width\":1440,\"height\":1080,\"service\":{\"@context\":\"http://iiif.io/api/image/2/context.json\",\"@id\":\"https://diyhistory.org/toyo/toyo3/iiif-img/2/5559\",\"profile\":\"http://iiif.io/api/image/2/level2.json\"}},\"on\":\"https://diyhistory.org/toyo/toyo3/iiif/2/ZKG053-3/canvas/p13\"}],\"metadata\":[{\"label\":\"Title\",\"value\":\"ZKG053\\u00d7500-3compo\"},{\"label\":\"Extent\",\"value\":\"500\"}]},{\"@id\":\"https://diyhistory.org/toyo/toyo3/iiif/2/ZKG053-3/canvas/p14\",\"@type\":\"sc:Canvas\",\"label\":{\"type\":\"literal\",\"property_id\":1,\"property_label\":\"Title\",\"is_public\":true,\"@value\":\"ZKG053\\u00d71000-3-3D\"},\"thumbnail\":{\"@id\":\"https://diyhistory.org/toyo/toyo3/files/medium/661f60bc737b4a0e2a5118571b4e0a9eba53e223.jpg\",\"@type\":\"dctypes:Image\",\"format\":\"image/jpeg\",\"width\":200,\"height\":150},\"width\":1440,\"height\":1080,\"images\":[{\"@id\":\"https://diyhistory.org/toyo/toyo3/iiif/2/ZKG053-3/annotation/p0014-image\",\"@type\":\"oa:Annotation\",\"motivation\":\"sc:painting\",\"resource\":{\"@id\":\"https://diyhistory.org/toyo/toyo3/iiif-img/2/5560/full/800,600/0/default.jpg\",\"@type\":\"dctypes:Image\",\"format\":\"image/jpeg\",\"width\":1440,\"height\":1080,\"service\":{\"@context\":\"http://iiif.io/api/image/2/context.json\",\"@id\":\"https://diyhistory.org/toyo/toyo3/iiif-img/2/5560\",\"profile\":\"http://iiif.io/api/image/2/level2.json\"}},\"on\":\"https://diyhistory.org/toyo/toyo3/iiif/2/ZKG053-3/canvas/p14\"}],\"metadata\":[{\"label\":\"Title\",\"value\":\"ZKG053\\u00d71000-3-3D\"},{\"label\":\"Extent\",\"value\":\"1000\"}]},{\"@id\":\"https://diyhistory.org/toyo/toyo3/iiif/2/ZKG053-3/canvas/p15\",\"@type\":\"sc:Canvas\",\"label\":{\"type\":\"literal\",\"property_id\":1,\"property_label\":\"Title\",\"is_public\":true,\"@value\":\"ZKG053\\u00d71000-3-3Dsca\"},\"thumbnail\":{\"@id\":\"https://diyhistory.org/toyo/toyo3/files/medium/28fc3ad3bfa11a6293fe251cfe76ef4a99a03b19.jpg\",\"@type\":\"dctypes:Image\",\"format\":\"image/jpeg\",\"width\":200,\"height\":150},\"width\":1440,\"height\":1080,\"images\":[{\"@id\":\"https://diyhistory.org/toyo/toyo3/iiif/2/ZKG053-3/annotation/p0015-image\",\"@type\":\"oa:Annotation\",\"motivation\":\"sc:painting\",\"resource\":{\"@id\":\"https://diyhistory.org/toyo/toyo3/iiif-img/2/5561/full/800,600/0/default.jpg\",\"@type\":\"dctypes:Image\",\"format\":\"image/jpeg\",\"width\":1440,\"height\":1080,\"service\":{\"@context\":\"http://iiif.io/api/image/2/context.json\",\"@id\":\"https://diyhistory.org/toyo/toyo3/iiif-img/2/5561\",\"profile\":\"http://iiif.io/api/image/2/level2.json\"}},\"on\":\"https://diyhistory.org/toyo/toyo3/iiif/2/ZKG053-3/canvas/p15\"}],\"metadata\":[{\"label\":\"Title\",\"value\":\"ZKG053\\u00d71000-3-3Dsca\"},{\"label\":\"Extent\",\"value\":\"1000\"}]},{\"@id\":\"https://diyhistory.org/toyo/toyo3/iiif/2/ZKG053-3/canvas/p16\",\"@type\":\"sc:Canvas\",\"label\":{\"type\":\"literal\",\"property_id\":1,\"property_label\":\"Title\",\"is_public\":true,\"@value\":\"ZKG053\\u00d71000-3-3to2D\"},\"thumbnail\":{\"@id\":\"https://diyhistory.org/toyo/toyo3/files/medium/9e6c5aa32e381a4fe69d21bd41ce4a83a33be845.jpg\",\"@type\":\"dctypes:Image\",\"format\":\"image/jpeg\",\"width\":200,\"height\":150},\"width\":1440,\"height\":1080,\"images\":[{\"@id\":\"https://diyhistory.org/toyo/toyo3/iiif/2/ZKG053-3/annotation/p0016-image\",\"@type\":\"oa:Annotation\",\"motivation\":\"sc:painting\",\"resource\":{\"@id\":\"https://diyhistory.org/toyo/toyo3/iiif-img/2/5562/full/800,600/0/default.jpg\",\"@type\":\"dctypes:Image\",\"format\":\"image/jpeg\",\"width\":1440,\"height\":1080,\"service\":{\"@context\":\"http://iiif.io/api/image/2/context.json\",\"@id\":\"https://diyhistory.org/toyo/toyo3/iiif-img/2/5562\",\"profile\":\"http://iiif.io/api/image/2/level2.json\"}},\"on\":\"https://diyhistory.org/toyo/toyo3/iiif/2/ZKG053-3/canvas/p16\"}],\"metadata\":[{\"label\":\"Title\",\"value\":\"ZKG053\\u00d71000-3-3to2D\"},{\"label\":\"Extent\",\"value\":\"1000\"}]},{\"@id\":\"https://diyhistory.org/toyo/toyo3/iiif/2/ZKG053-3/canvas/p17\",\"@type\":\"sc:Canvas\",\"label\":{\"type\":\"literal\",\"property_id\":1,\"property_label\":\"Title\",\"is_public\":true,\"@value\":\"ZKG053\\u00d71000-3\"},\"thumbnail\":{\"@id\":\"https://diyhistory.org/toyo/toyo3/files/medium/62292ce15ecbb4045549436e911ba152d3aa2715.jpg\",\"@type\":\"dctypes:Image\",\"format\":\"image/jpeg\",\"width\":200,\"height\":150},\"width\":1440,\"height\":1080,\"images\":[{\"@id\":\"https://diyhistory.org/toyo/toyo3/iiif/2/ZKG053-3/annotation/p0017-image\",\"@type\":\"oa:Annotation\",\"motivation\":\"sc:painting\",\"resource\":{\"@id\":\"https://diyhistory.org/toyo/toyo3/iiif-img/2/5563/full/800,600/0/default.jpg\",\"@type\":\"dctypes:Image\",\"format\":\"image/jpeg\",\"width\":1440,\"height\":1080,\"service\":{\"@context\":\"http://iiif.io/api/image/2/context.json\",\"@id\":\"https://diyhistory.org/toyo/toyo3/iiif-img/2/5563\",\"profile\":\"http://iiif.io/api/image/2/level2.json\"}},\"on\":\"https://diyhistory.org/toyo/toyo3/iiif/2/ZKG053-3/canvas/p17\"}],\"metadata\":[{\"label\":\"Title\",\"value\":\"ZKG053\\u00d71000-3\"},{\"label\":\"Extent\",\"value\":\"1000\"}]},{\"@id\":\"https://diyhistory.org/toyo/toyo3/iiif/2/ZKG053-3/canvas/p18\",\"@type\":\"sc:Canvas\",\"label\":{\"type\":\"literal\",\"property_id\":1,\"property_label\":\"Title\",\"is_public\":true,\"@value\":\"ZKG053\\u00d71000-3compo\"},\"thumbnail\":{\"@id\":\"https://diyhistory.org/toyo/toyo3/files/medium/06b908f774eac955ff8609a9ae48273a6c1d8494.jpg\",\"@type\":\"dctypes:Image\",\"format\":\"image/jpeg\",\"width\":200,\"height\":150},\"width\":1440,\"height\":1080,\"images\":[{\"@id\":\"https://diyhistory.org/toyo/toyo3/iiif/2/ZKG053-3/annotation/p0018-image\",\"@type\":\"oa:Annotation\",\"motivation\":\"sc:painting\",\"resource\":{\"@id\":\"https://diyhistory.org/toyo/toyo3/iiif-img/2/5564/full/800,600/0/default.jpg\",\"@type\":\"dctypes:Image\",\"format\":\"image/jpeg\",\"width\":1440,\"height\":1080,\"service\":{\"@context\":\"http://iiif.io/api/image/2/context.json\",\"@id\":\"https://diyhistory.org/toyo/toyo3/iiif-img/2/5564\",\"profile\":\"http://iiif.io/api/image/2/level2.json\"}},\"on\":\"https://diyhistory.org/toyo/toyo3/iiif/2/ZKG053-3/canvas/p18\"}],\"metadata\":[{\"label\":\"Title\",\"value\":\"ZKG053\\u00d71000-3compo\"},{\"label\":\"Extent\",\"value\":\"1000\"}]}]}]}"
        },
        {
            "element": {
                "id": 58,
                "name": "IIIF Type",
                "resource": "elements",
                "url": "https://diyhistory.org/toyo/omekac3/api/elements/58"
            },
            "element_set": {
                "id": 6,
                "name": "IIIF Collection Metadata",
                "resource": "element_sets",
                "url": "https://diyhistory.org/toyo/omekac3/api/element_sets/6"
            },
            "html": false,
            "text": "Manifest"
        },
        {
            "element": {
                "id": 59,
                "name": "Parent Collection",
                "resource": "elements",
                "url": "https://diyhistory.org/toyo/omekac3/api/elements/59"
            },
            "element_set": {
                "id": 6,
                "name": "IIIF Collection Metadata",
                "resource": "element_sets",
                "url": "https://diyhistory.org/toyo/omekac3/api/element_sets/6"
            },
            "html": false,
            "text": "d7884de6-5890-4002-967b-25f599af04bb"
        },
        {
            "element": {
                "id": 61,
                "name": "UUID",
                "resource": "elements",
                "url": "https://diyhistory.org/toyo/omekac3/api/elements/61"
            },
            "element_set": {
                "id": 6,
                "name": "IIIF Collection Metadata",
                "resource": "element_sets",
                "url": "https://diyhistory.org/toyo/omekac3/api/element_sets/6"
            },
            "html": false,
            "text": "3a0ceb97-237c-4cdc-891c-0a7ea91f81e8"
        }
    ],
    "extended_resources": [],
    "featured": false,
    "id": 324,
    "items": {
        "count": 18,
        "resource": "items",
        "url": "https://diyhistory.org/toyo/omekac3/api/items?collection=324"
    },
    "modified": "2021-02-10T14:05:14+00:00",
    "owner": {
        "id": 1,
        "resource": "users",
        "url": "https://diyhistory.org/toyo/omekac3/api/users/1"
    },
    "public": false,
    "url": "https://diyhistory.org/toyo/omekac3/api/collections/324"
}