{
    "@id": "https://diyhistory.org/toyo/omekac3/api/5669.json",
    "added": "2021-02-22T05:55:45+00:00",
    "collection": null,
    "element_texts": [
        {
            "element": {
                "id": 50,
                "name": "Title",
                "resource": "elements",
                "url": "https://diyhistory.org/toyo/omekac3/api/elements/50"
            },
            "element_set": {
                "id": 1,
                "name": "Dublin Core",
                "resource": "element_sets",
                "url": "https://diyhistory.org/toyo/omekac3/api/element_sets/1"
            },
            "html": false,
            "text": "Annotation: \"夾雑物\""
        },
        {
            "element": {
                "id": 62,
                "name": "On Canvas",
                "resource": "elements",
                "url": "https://diyhistory.org/toyo/omekac3/api/elements/62"
            },
            "element_set": {
                "id": 3,
                "name": "Item Type Metadata",
                "resource": "element_sets",
                "url": "https://diyhistory.org/toyo/omekac3/api/element_sets/3"
            },
            "html": false,
            "text": "32a99b30-a439-4e46-9e31-1503c0027ee6"
        },
        {
            "element": {
                "id": 63,
                "name": "Selector",
                "resource": "elements",
                "url": "https://diyhistory.org/toyo/omekac3/api/elements/63"
            },
            "element_set": {
                "id": 3,
                "name": "Item Type Metadata",
                "resource": "element_sets",
                "url": "https://diyhistory.org/toyo/omekac3/api/element_sets/3"
            },
            "html": false,
            "text": "<svg xmlns='http://www.w3.org/2000/svg'><path xmlns=\"http://www.w3.org/2000/svg\" d=\"M684.85921,411.2852h85.80144v0h85.80144v143.31047v143.31047h-85.80144h-85.80144v-143.31047z\" data-paper-data=\"{&quot;strokeWidth&quot;:1,&quot;rotation&quot;:0,&quot;deleteIcon&quot;:null,&quot;rotationIcon&quot;:null,&quot;group&quot;:null,&quot;editable&quot;:true,&quot;annotation&quot;:null}\" id=\"rectangle_b415e5ef-2caf-4fac-b389-9fbbcb5db6a9\" fill-opacity=\"0\" fill=\"#00bfff\" fill-rule=\"nonzero\" stroke=\"#00bfff\" stroke-width=\"1\" stroke-linecap=\"butt\" stroke-linejoin=\"miter\" stroke-miterlimit=\"10\" stroke-dasharray=\"\" stroke-dashoffset=\"0\" font-family=\"none\" font-weight=\"none\" font-size=\"none\" text-anchor=\"none\" style=\"mix-blend-mode: normal\"/></svg>"
        },
        {
            "element": {
                "id": 63,
                "name": "Selector",
                "resource": "elements",
                "url": "https://diyhistory.org/toyo/omekac3/api/elements/63"
            },
            "element_set": {
                "id": 3,
                "name": "Item Type Metadata",
                "resource": "element_sets",
                "url": "https://diyhistory.org/toyo/omekac3/api/element_sets/3"
            },
            "html": false,
            "text": "<svg xmlns='http://www.w3.org/2000/svg'><path xmlns=\"http://www.w3.org/2000/svg\" d=\"M530.85199,440.52708h39.98917v0h39.98917v36.09025v36.09025h-39.98917h-39.98917v-36.09025z\" data-paper-data=\"{&quot;strokeWidth&quot;:1,&quot;rotation&quot;:0,&quot;deleteIcon&quot;:null,&quot;rotationIcon&quot;:null,&quot;group&quot;:null,&quot;editable&quot;:true,&quot;annotation&quot;:null}\" id=\"rectangle_acec6185-fbea-4b9c-91e4-04feecafeb79\" fill-opacity=\"0\" fill=\"#00bfff\" fill-rule=\"nonzero\" stroke=\"#00bfff\" stroke-width=\"1\" stroke-linecap=\"butt\" stroke-linejoin=\"miter\" stroke-miterlimit=\"10\" stroke-dasharray=\"\" stroke-dashoffset=\"0\" font-family=\"none\" font-weight=\"none\" font-size=\"none\" text-anchor=\"none\" style=\"mix-blend-mode: normal\"/></svg>"
        },
        {
            "element": {
                "id": 63,
                "name": "Selector",
                "resource": "elements",
                "url": "https://diyhistory.org/toyo/omekac3/api/elements/63"
            },
            "element_set": {
                "id": 3,
                "name": "Item Type Metadata",
                "resource": "element_sets",
                "url": "https://diyhistory.org/toyo/omekac3/api/element_sets/3"
            },
            "html": false,
            "text": "<svg xmlns='http://www.w3.org/2000/svg'><path xmlns=\"http://www.w3.org/2000/svg\" d=\"M261.82671,925.94224h18.54513v0h18.54513v16.59567v16.59567h-18.54513h-18.54513v-16.59567z\" data-paper-data=\"{&quot;strokeWidth&quot;:1,&quot;rotation&quot;:0,&quot;deleteIcon&quot;:null,&quot;rotationIcon&quot;:null,&quot;group&quot;:null,&quot;editable&quot;:true,&quot;annotation&quot;:null}\" id=\"rectangle_ec717631-c9b0-467a-91c1-0d8a5019027f\" fill-opacity=\"0\" fill=\"#00bfff\" fill-rule=\"nonzero\" stroke=\"#00bfff\" stroke-width=\"1\" stroke-linecap=\"butt\" stroke-linejoin=\"miter\" stroke-miterlimit=\"10\" stroke-dasharray=\"\" stroke-dashoffset=\"0\" font-family=\"none\" font-weight=\"none\" font-size=\"none\" text-anchor=\"none\" style=\"mix-blend-mode: normal\"/></svg>"
        },
        {
            "element": {
                "id": 63,
                "name": "Selector",
                "resource": "elements",
                "url": "https://diyhistory.org/toyo/omekac3/api/elements/63"
            },
            "element_set": {
                "id": 3,
                "name": "Item Type Metadata",
                "resource": "element_sets",
                "url": "https://diyhistory.org/toyo/omekac3/api/element_sets/3"
            },
            "html": false,
            "text": "<svg xmlns='http://www.w3.org/2000/svg'><path xmlns=\"http://www.w3.org/2000/svg\" d=\"M279.37184,756.33935h24.3935v0h24.3935v16.59567v16.59567h-24.3935h-24.3935v-16.59567z\" data-paper-data=\"{&quot;strokeWidth&quot;:1,&quot;rotation&quot;:0,&quot;deleteIcon&quot;:null,&quot;rotationIcon&quot;:null,&quot;group&quot;:null,&quot;editable&quot;:true,&quot;annotation&quot;:null}\" id=\"rectangle_7e0b1105-db0d-4213-bf0f-46af772f42a4\" fill-opacity=\"0\" fill=\"#00bfff\" fill-rule=\"nonzero\" stroke=\"#00bfff\" stroke-width=\"1\" stroke-linecap=\"butt\" stroke-linejoin=\"miter\" stroke-miterlimit=\"10\" stroke-dasharray=\"\" stroke-dashoffset=\"0\" font-family=\"none\" font-weight=\"none\" font-size=\"none\" text-anchor=\"none\" style=\"mix-blend-mode: normal\"/></svg>"
        },
        {
            "element": {
                "id": 63,
                "name": "Selector",
                "resource": "elements",
                "url": "https://diyhistory.org/toyo/omekac3/api/elements/63"
            },
            "element_set": {
                "id": 3,
                "name": "Item Type Metadata",
                "resource": "element_sets",
                "url": "https://diyhistory.org/toyo/omekac3/api/element_sets/3"
            },
            "html": false,
            "text": "<svg xmlns='http://www.w3.org/2000/svg'><path xmlns=\"http://www.w3.org/2000/svg\" d=\"M776.48375,729.04693h24.3935v0h24.3935v18.54513v18.54513h-24.3935h-24.3935v-18.54513z\" data-paper-data=\"{&quot;strokeWidth&quot;:1,&quot;rotation&quot;:0,&quot;deleteIcon&quot;:null,&quot;rotationIcon&quot;:null,&quot;group&quot;:null,&quot;editable&quot;:true,&quot;annotation&quot;:null}\" id=\"rectangle_9a252599-dce9-4143-89b3-b88ce918190f\" fill-opacity=\"0\" fill=\"#00bfff\" fill-rule=\"nonzero\" stroke=\"#00bfff\" stroke-width=\"1\" stroke-linecap=\"butt\" stroke-linejoin=\"miter\" stroke-miterlimit=\"10\" stroke-dasharray=\"\" stroke-dashoffset=\"0\" font-family=\"none\" font-weight=\"none\" font-size=\"none\" text-anchor=\"none\" style=\"mix-blend-mode: normal\"/></svg>"
        },
        {
            "element": {
                "id": 63,
                "name": "Selector",
                "resource": "elements",
                "url": "https://diyhistory.org/toyo/omekac3/api/elements/63"
            },
            "element_set": {
                "id": 3,
                "name": "Item Type Metadata",
                "resource": "element_sets",
                "url": "https://diyhistory.org/toyo/omekac3/api/element_sets/3"
            },
            "html": false,
            "text": "<svg xmlns='http://www.w3.org/2000/svg'><path xmlns=\"http://www.w3.org/2000/svg\" d=\"M1365.22022,278.72202h36.09025v0h36.09025v31.21661v31.21661h-36.09025h-36.09025v-31.21661z\" data-paper-data=\"{&quot;strokeWidth&quot;:1,&quot;rotation&quot;:0,&quot;deleteIcon&quot;:null,&quot;rotationIcon&quot;:null,&quot;group&quot;:null,&quot;editable&quot;:true,&quot;annotation&quot;:null}\" id=\"rectangle_8fb4514c-fc5b-4c87-950c-dbdb5b1ffa88\" fill-opacity=\"0\" fill=\"#00bfff\" fill-rule=\"nonzero\" stroke=\"#00bfff\" stroke-width=\"1\" stroke-linecap=\"butt\" stroke-linejoin=\"miter\" stroke-miterlimit=\"10\" stroke-dasharray=\"\" stroke-dashoffset=\"0\" font-family=\"none\" font-weight=\"none\" font-size=\"none\" text-anchor=\"none\" style=\"mix-blend-mode: normal\"/></svg>"
        },
        {
            "element": {
                "id": 64,
                "name": "Annotated Region",
                "resource": "elements",
                "url": "https://diyhistory.org/toyo/omekac3/api/elements/64"
            },
            "element_set": {
                "id": 3,
                "name": "Item Type Metadata",
                "resource": "element_sets",
                "url": "https://diyhistory.org/toyo/omekac3/api/element_sets/3"
            },
            "html": false,
            "text": "685,411,172,287"
        },
        {
            "element": {
                "id": 64,
                "name": "Annotated Region",
                "resource": "elements",
                "url": "https://diyhistory.org/toyo/omekac3/api/elements/64"
            },
            "element_set": {
                "id": 3,
                "name": "Item Type Metadata",
                "resource": "element_sets",
                "url": "https://diyhistory.org/toyo/omekac3/api/element_sets/3"
            },
            "html": false,
            "text": "531,441,80,72"
        },
        {
            "element": {
                "id": 64,
                "name": "Annotated Region",
                "resource": "elements",
                "url": "https://diyhistory.org/toyo/omekac3/api/elements/64"
            },
            "element_set": {
                "id": 3,
                "name": "Item Type Metadata",
                "resource": "element_sets",
                "url": "https://diyhistory.org/toyo/omekac3/api/element_sets/3"
            },
            "html": false,
            "text": "262,926,37,33"
        },
        {
            "element": {
                "id": 64,
                "name": "Annotated Region",
                "resource": "elements",
                "url": "https://diyhistory.org/toyo/omekac3/api/elements/64"
            },
            "element_set": {
                "id": 3,
                "name": "Item Type Metadata",
                "resource": "element_sets",
                "url": "https://diyhistory.org/toyo/omekac3/api/element_sets/3"
            },
            "html": false,
            "text": "279,756,49,33"
        },
        {
            "element": {
                "id": 64,
                "name": "Annotated Region",
                "resource": "elements",
                "url": "https://diyhistory.org/toyo/omekac3/api/elements/64"
            },
            "element_set": {
                "id": 3,
                "name": "Item Type Metadata",
                "resource": "element_sets",
                "url": "https://diyhistory.org/toyo/omekac3/api/element_sets/3"
            },
            "html": false,
            "text": "776,729,49,37"
        },
        {
            "element": {
                "id": 64,
                "name": "Annotated Region",
                "resource": "elements",
                "url": "https://diyhistory.org/toyo/omekac3/api/elements/64"
            },
            "element_set": {
                "id": 3,
                "name": "Item Type Metadata",
                "resource": "element_sets",
                "url": "https://diyhistory.org/toyo/omekac3/api/element_sets/3"
            },
            "html": false,
            "text": "1365,279,72,62"
        },
        {
            "element": {
                "id": 1,
                "name": "Text",
                "resource": "elements",
                "url": "https://diyhistory.org/toyo/omekac3/api/elements/1"
            },
            "element_set": {
                "id": 3,
                "name": "Item Type Metadata",
                "resource": "element_sets",
                "url": "https://diyhistory.org/toyo/omekac3/api/element_sets/3"
            },
            "html": true,
            "text": "<p>夾雑物</p>"
        },
        {
            "element": {
                "id": 65,
                "name": "UUID",
                "resource": "elements",
                "url": "https://diyhistory.org/toyo/omekac3/api/elements/65"
            },
            "element_set": {
                "id": 5,
                "name": "IIIF Item Metadata",
                "resource": "element_sets",
                "url": "https://diyhistory.org/toyo/omekac3/api/element_sets/5"
            },
            "html": false,
            "text": "3977eda8-c92b-418d-962d-f741632f3357"
        },
        {
            "element": {
                "id": 55,
                "name": "Original @id",
                "resource": "elements",
                "url": "https://diyhistory.org/toyo/omekac3/api/elements/55"
            },
            "element_set": {
                "id": 5,
                "name": "IIIF Item Metadata",
                "resource": "element_sets",
                "url": "https://diyhistory.org/toyo/omekac3/api/element_sets/5"
            },
            "html": false,
            "text": "https://diyhistory.org/toyo/omekac3/oa/items/5669/anno.json"
        },
        {
            "element": {
                "id": 56,
                "name": "JSON Data",
                "resource": "elements",
                "url": "https://diyhistory.org/toyo/omekac3/api/elements/56"
            },
            "element_set": {
                "id": 5,
                "name": "IIIF Item Metadata",
                "resource": "element_sets",
                "url": "https://diyhistory.org/toyo/omekac3/api/element_sets/5"
            },
            "html": false,
            "text": "{\"@context\":\"http://iiif.io/api/presentation/2/context.json\",\"@type\":\"oa:Annotation\",\"motivation\":\"oa:commenting\",\"resource\":[{\"@type\":\"dctypes:Text\",\"format\":\"text/html\",\"chars\":\"<p>\\u593e\\u96d1\\u7269</p>\"}],\"on\":[{\"@type\":\"oa:SpecificResource\",\"full\":\"https://diyhistory.org/toyo/toyo3/iiif/2/PBG004-5/canvas/p3\",\"selector\":{\"@type\":\"oa:Choice\",\"default\":{\"@type\":\"oa:FragmentSelector\",\"value\":\"xywh=685,411,172,287\"},\"item\":{\"@type\":\"oa:SvgSelector\",\"value\":\"<svg xmlns='http://www.w3.org/2000/svg'><path xmlns=\\\"http://www.w3.org/2000/svg\\\" d=\\\"M684.85921,411.2852h85.80144v0h85.80144v143.31047v143.31047h-85.80144h-85.80144v-143.31047z\\\" data-paper-data=\\\"{&quot;strokeWidth&quot;:1,&quot;rotation&quot;:0,&quot;deleteIcon&quot;:null,&quot;rotationIcon&quot;:null,&quot;group&quot;:null,&quot;editable&quot;:true,&quot;annotation&quot;:null}\\\" id=\\\"rectangle_b415e5ef-2caf-4fac-b389-9fbbcb5db6a9\\\" fill-opacity=\\\"0\\\" fill=\\\"#00bfff\\\" fill-rule=\\\"nonzero\\\" stroke=\\\"#00bfff\\\" stroke-width=\\\"1\\\" stroke-linecap=\\\"butt\\\" stroke-linejoin=\\\"miter\\\" stroke-miterlimit=\\\"10\\\" stroke-dasharray=\\\"\\\" stroke-dashoffset=\\\"0\\\" font-family=\\\"none\\\" font-weight=\\\"none\\\" font-size=\\\"none\\\" text-anchor=\\\"none\\\" style=\\\"mix-blend-mode: normal\\\"/></svg>\"}},\"within\":{\"@id\":\"https://diyhistory.org/toyo/omekac3/oa/collections/24/manifest.json\",\"@type\":\"sc:Manifest\"}},{\"@type\":\"oa:SpecificResource\",\"full\":\"https://diyhistory.org/toyo/toyo3/iiif/2/PBG004-5/canvas/p3\",\"selector\":{\"@type\":\"oa:Choice\",\"default\":{\"@type\":\"oa:FragmentSelector\",\"value\":\"xywh=531,441,80,72\"},\"item\":{\"@type\":\"oa:SvgSelector\",\"value\":\"<svg xmlns='http://www.w3.org/2000/svg'><path xmlns=\\\"http://www.w3.org/2000/svg\\\" d=\\\"M530.85199,440.52708h39.98917v0h39.98917v36.09025v36.09025h-39.98917h-39.98917v-36.09025z\\\" data-paper-data=\\\"{&quot;strokeWidth&quot;:1,&quot;rotation&quot;:0,&quot;deleteIcon&quot;:null,&quot;rotationIcon&quot;:null,&quot;group&quot;:null,&quot;editable&quot;:true,&quot;annotation&quot;:null}\\\" id=\\\"rectangle_acec6185-fbea-4b9c-91e4-04feecafeb79\\\" fill-opacity=\\\"0\\\" fill=\\\"#00bfff\\\" fill-rule=\\\"nonzero\\\" stroke=\\\"#00bfff\\\" stroke-width=\\\"1\\\" stroke-linecap=\\\"butt\\\" stroke-linejoin=\\\"miter\\\" stroke-miterlimit=\\\"10\\\" stroke-dasharray=\\\"\\\" stroke-dashoffset=\\\"0\\\" font-family=\\\"none\\\" font-weight=\\\"none\\\" font-size=\\\"none\\\" text-anchor=\\\"none\\\" style=\\\"mix-blend-mode: normal\\\"/></svg>\"}},\"within\":{\"@id\":\"https://diyhistory.org/toyo/omekac3/oa/collections/24/manifest.json\",\"@type\":\"sc:Manifest\"}},{\"@type\":\"oa:SpecificResource\",\"full\":\"https://diyhistory.org/toyo/toyo3/iiif/2/PBG004-5/canvas/p3\",\"selector\":{\"@type\":\"oa:Choice\",\"default\":{\"@type\":\"oa:FragmentSelector\",\"value\":\"xywh=262,926,37,33\"},\"item\":{\"@type\":\"oa:SvgSelector\",\"value\":\"<svg xmlns='http://www.w3.org/2000/svg'><path xmlns=\\\"http://www.w3.org/2000/svg\\\" d=\\\"M261.82671,925.94224h18.54513v0h18.54513v16.59567v16.59567h-18.54513h-18.54513v-16.59567z\\\" data-paper-data=\\\"{&quot;strokeWidth&quot;:1,&quot;rotation&quot;:0,&quot;deleteIcon&quot;:null,&quot;rotationIcon&quot;:null,&quot;group&quot;:null,&quot;editable&quot;:true,&quot;annotation&quot;:null}\\\" id=\\\"rectangle_ec717631-c9b0-467a-91c1-0d8a5019027f\\\" fill-opacity=\\\"0\\\" fill=\\\"#00bfff\\\" fill-rule=\\\"nonzero\\\" stroke=\\\"#00bfff\\\" stroke-width=\\\"1\\\" stroke-linecap=\\\"butt\\\" stroke-linejoin=\\\"miter\\\" stroke-miterlimit=\\\"10\\\" stroke-dasharray=\\\"\\\" stroke-dashoffset=\\\"0\\\" font-family=\\\"none\\\" font-weight=\\\"none\\\" font-size=\\\"none\\\" text-anchor=\\\"none\\\" style=\\\"mix-blend-mode: normal\\\"/></svg>\"}},\"within\":{\"@id\":\"https://diyhistory.org/toyo/omekac3/oa/collections/24/manifest.json\",\"@type\":\"sc:Manifest\"}},{\"@type\":\"oa:SpecificResource\",\"full\":\"https://diyhistory.org/toyo/toyo3/iiif/2/PBG004-5/canvas/p3\",\"selector\":{\"@type\":\"oa:Choice\",\"default\":{\"@type\":\"oa:FragmentSelector\",\"value\":\"xywh=279,756,49,33\"},\"item\":{\"@type\":\"oa:SvgSelector\",\"value\":\"<svg xmlns='http://www.w3.org/2000/svg'><path xmlns=\\\"http://www.w3.org/2000/svg\\\" d=\\\"M279.37184,756.33935h24.3935v0h24.3935v16.59567v16.59567h-24.3935h-24.3935v-16.59567z\\\" data-paper-data=\\\"{&quot;strokeWidth&quot;:1,&quot;rotation&quot;:0,&quot;deleteIcon&quot;:null,&quot;rotationIcon&quot;:null,&quot;group&quot;:null,&quot;editable&quot;:true,&quot;annotation&quot;:null}\\\" id=\\\"rectangle_7e0b1105-db0d-4213-bf0f-46af772f42a4\\\" fill-opacity=\\\"0\\\" fill=\\\"#00bfff\\\" fill-rule=\\\"nonzero\\\" stroke=\\\"#00bfff\\\" stroke-width=\\\"1\\\" stroke-linecap=\\\"butt\\\" stroke-linejoin=\\\"miter\\\" stroke-miterlimit=\\\"10\\\" stroke-dasharray=\\\"\\\" stroke-dashoffset=\\\"0\\\" font-family=\\\"none\\\" font-weight=\\\"none\\\" font-size=\\\"none\\\" text-anchor=\\\"none\\\" style=\\\"mix-blend-mode: normal\\\"/></svg>\"}},\"within\":{\"@id\":\"https://diyhistory.org/toyo/omekac3/oa/collections/24/manifest.json\",\"@type\":\"sc:Manifest\"}},{\"@type\":\"oa:SpecificResource\",\"full\":\"https://diyhistory.org/toyo/toyo3/iiif/2/PBG004-5/canvas/p3\",\"selector\":{\"@type\":\"oa:Choice\",\"default\":{\"@type\":\"oa:FragmentSelector\",\"value\":\"xywh=776,729,49,37\"},\"item\":{\"@type\":\"oa:SvgSelector\",\"value\":\"<svg xmlns='http://www.w3.org/2000/svg'><path xmlns=\\\"http://www.w3.org/2000/svg\\\" d=\\\"M776.48375,729.04693h24.3935v0h24.3935v18.54513v18.54513h-24.3935h-24.3935v-18.54513z\\\" data-paper-data=\\\"{&quot;strokeWidth&quot;:1,&quot;rotation&quot;:0,&quot;deleteIcon&quot;:null,&quot;rotationIcon&quot;:null,&quot;group&quot;:null,&quot;editable&quot;:true,&quot;annotation&quot;:null}\\\" id=\\\"rectangle_9a252599-dce9-4143-89b3-b88ce918190f\\\" fill-opacity=\\\"0\\\" fill=\\\"#00bfff\\\" fill-rule=\\\"nonzero\\\" stroke=\\\"#00bfff\\\" stroke-width=\\\"1\\\" stroke-linecap=\\\"butt\\\" stroke-linejoin=\\\"miter\\\" stroke-miterlimit=\\\"10\\\" stroke-dasharray=\\\"\\\" stroke-dashoffset=\\\"0\\\" font-family=\\\"none\\\" font-weight=\\\"none\\\" font-size=\\\"none\\\" text-anchor=\\\"none\\\" style=\\\"mix-blend-mode: normal\\\"/></svg>\"}},\"within\":{\"@id\":\"https://diyhistory.org/toyo/omekac3/oa/collections/24/manifest.json\",\"@type\":\"sc:Manifest\"}},{\"@type\":\"oa:SpecificResource\",\"full\":\"https://diyhistory.org/toyo/toyo3/iiif/2/PBG004-5/canvas/p3\",\"selector\":{\"@type\":\"oa:Choice\",\"default\":{\"@type\":\"oa:FragmentSelector\",\"value\":\"xywh=1365,279,72,62\"},\"item\":{\"@type\":\"oa:SvgSelector\",\"value\":\"<svg xmlns='http://www.w3.org/2000/svg'><path xmlns=\\\"http://www.w3.org/2000/svg\\\" d=\\\"M1365.22022,278.72202h36.09025v0h36.09025v31.21661v31.21661h-36.09025h-36.09025v-31.21661z\\\" data-paper-data=\\\"{&quot;strokeWidth&quot;:1,&quot;rotation&quot;:0,&quot;deleteIcon&quot;:null,&quot;rotationIcon&quot;:null,&quot;group&quot;:null,&quot;editable&quot;:true,&quot;annotation&quot;:null}\\\" id=\\\"rectangle_8fb4514c-fc5b-4c87-950c-dbdb5b1ffa88\\\" fill-opacity=\\\"0\\\" fill=\\\"#00bfff\\\" fill-rule=\\\"nonzero\\\" stroke=\\\"#00bfff\\\" stroke-width=\\\"1\\\" stroke-linecap=\\\"butt\\\" stroke-linejoin=\\\"miter\\\" stroke-miterlimit=\\\"10\\\" stroke-dasharray=\\\"\\\" stroke-dashoffset=\\\"0\\\" font-family=\\\"none\\\" font-weight=\\\"none\\\" font-size=\\\"none\\\" text-anchor=\\\"none\\\" style=\\\"mix-blend-mode: normal\\\"/></svg>\"}},\"within\":{\"@id\":\"https://diyhistory.org/toyo/omekac3/oa/collections/24/manifest.json\",\"@type\":\"sc:Manifest\"}}],\"@id\":\"https://diyhistory.org/toyo/omekac3/oa/items/5669/anno.json\"}"
        }
    ],
    "extended_resources": [],
    "featured": false,
    "files": {
        "count": 0,
        "resource": "files",
        "url": "https://diyhistory.org/toyo/omekac3/api/files?item=5669"
    },
    "id": 5669,
    "item_type": {
        "id": 18,
        "name": "Annotation",
        "resource": "item_types",
        "url": "https://diyhistory.org/toyo/omekac3/api/item_types/18"
    },
    "modified": "2021-02-22T05:55:45+00:00",
    "owner": {
        "id": 5,
        "resource": "users",
        "url": "https://diyhistory.org/toyo/omekac3/api/users/5"
    },
    "public": false,
    "tags": [],
    "url": "https://diyhistory.org/toyo/omekac3/api/items/5669"
}