{
    "@id": "https://diyhistory.org/toyo/omekac3/api/5697.json",
    "added": "2021-02-22T06:36:51+00:00",
    "collection": null,
    "element_texts": [
        {
            "element": {
                "id": 50,
                "name": "Title",
                "resource": "elements",
                "url": "https://diyhistory.org/toyo/omekac3/api/elements/50"
            },
            "element_set": {
                "id": 1,
                "name": "Dublin Core",
                "resource": "element_sets",
                "url": "https://diyhistory.org/toyo/omekac3/api/element_sets/1"
            },
            "html": false,
            "text": "Annotation: \"夾雑物\""
        },
        {
            "element": {
                "id": 62,
                "name": "On Canvas",
                "resource": "elements",
                "url": "https://diyhistory.org/toyo/omekac3/api/elements/62"
            },
            "element_set": {
                "id": 3,
                "name": "Item Type Metadata",
                "resource": "element_sets",
                "url": "https://diyhistory.org/toyo/omekac3/api/element_sets/3"
            },
            "html": false,
            "text": "c21eb647-d55e-4411-bf4b-6567bfb83e71"
        },
        {
            "element": {
                "id": 63,
                "name": "Selector",
                "resource": "elements",
                "url": "https://diyhistory.org/toyo/omekac3/api/elements/63"
            },
            "element_set": {
                "id": 3,
                "name": "Item Type Metadata",
                "resource": "element_sets",
                "url": "https://diyhistory.org/toyo/omekac3/api/element_sets/3"
            },
            "html": false,
            "text": "<svg xmlns='http://www.w3.org/2000/svg'><path xmlns=\"http://www.w3.org/2000/svg\" d=\"M279.96837,267.90505l424.52465,67.64893v0l424.52465,67.64893l-28.38111,178.10306l-28.38111,178.10306l-424.52465,-67.64893l-424.52465,-67.64893l28.38111,-178.10306z\" data-paper-data=\"{&quot;strokeWidth&quot;:1,&quot;rotation&quot;:9.054082566192164,&quot;deleteIcon&quot;:null,&quot;rotationIcon&quot;:null,&quot;group&quot;:null,&quot;editable&quot;:true,&quot;annotation&quot;:null}\" id=\"rectangle_068cb630-dcca-4335-8abb-fb085e1893dd\" fill-opacity=\"0\" fill=\"#00bfff\" fill-rule=\"nonzero\" stroke=\"#00bfff\" stroke-width=\"1\" stroke-linecap=\"butt\" stroke-linejoin=\"miter\" stroke-miterlimit=\"10\" stroke-dasharray=\"\" stroke-dashoffset=\"0\" font-family=\"none\" font-weight=\"none\" font-size=\"none\" text-anchor=\"none\" style=\"mix-blend-mode: normal\"/></svg>"
        },
        {
            "element": {
                "id": 64,
                "name": "Annotated Region",
                "resource": "elements",
                "url": "https://diyhistory.org/toyo/omekac3/api/elements/64"
            },
            "element_set": {
                "id": 3,
                "name": "Item Type Metadata",
                "resource": "element_sets",
                "url": "https://diyhistory.org/toyo/omekac3/api/element_sets/3"
            },
            "html": false,
            "text": "223,268,906,492"
        },
        {
            "element": {
                "id": 1,
                "name": "Text",
                "resource": "elements",
                "url": "https://diyhistory.org/toyo/omekac3/api/elements/1"
            },
            "element_set": {
                "id": 3,
                "name": "Item Type Metadata",
                "resource": "element_sets",
                "url": "https://diyhistory.org/toyo/omekac3/api/element_sets/3"
            },
            "html": true,
            "text": "<p>夾雑物</p>"
        },
        {
            "element": {
                "id": 65,
                "name": "UUID",
                "resource": "elements",
                "url": "https://diyhistory.org/toyo/omekac3/api/elements/65"
            },
            "element_set": {
                "id": 5,
                "name": "IIIF Item Metadata",
                "resource": "element_sets",
                "url": "https://diyhistory.org/toyo/omekac3/api/element_sets/5"
            },
            "html": false,
            "text": "c0f0bb9e-d139-4f1e-be94-f6db597896ea"
        },
        {
            "element": {
                "id": 55,
                "name": "Original @id",
                "resource": "elements",
                "url": "https://diyhistory.org/toyo/omekac3/api/elements/55"
            },
            "element_set": {
                "id": 5,
                "name": "IIIF Item Metadata",
                "resource": "element_sets",
                "url": "https://diyhistory.org/toyo/omekac3/api/element_sets/5"
            },
            "html": false,
            "text": "https://diyhistory.org/toyo/omekac3/oa/items/5697/anno.json"
        },
        {
            "element": {
                "id": 56,
                "name": "JSON Data",
                "resource": "elements",
                "url": "https://diyhistory.org/toyo/omekac3/api/elements/56"
            },
            "element_set": {
                "id": 5,
                "name": "IIIF Item Metadata",
                "resource": "element_sets",
                "url": "https://diyhistory.org/toyo/omekac3/api/element_sets/5"
            },
            "html": false,
            "text": "{\"@context\":\"http://iiif.io/api/presentation/2/context.json\",\"@type\":\"oa:Annotation\",\"motivation\":\"oa:commenting\",\"resource\":[{\"@type\":\"dctypes:Text\",\"format\":\"text/html\",\"chars\":\"<p>\\u593e\\u96d1\\u7269</p>\"}],\"on\":[{\"@type\":\"oa:SpecificResource\",\"full\":\"https://diyhistory.org/toyo/toyo3/iiif/2/PCG006-3/canvas/p4\",\"selector\":{\"@type\":\"oa:Choice\",\"default\":{\"@type\":\"oa:FragmentSelector\",\"value\":\"xywh=223,268,906,492\"},\"item\":{\"@type\":\"oa:SvgSelector\",\"value\":\"<svg xmlns='http://www.w3.org/2000/svg'><path xmlns=\\\"http://www.w3.org/2000/svg\\\" d=\\\"M279.96837,267.90505l424.52465,67.64893v0l424.52465,67.64893l-28.38111,178.10306l-28.38111,178.10306l-424.52465,-67.64893l-424.52465,-67.64893l28.38111,-178.10306z\\\" data-paper-data=\\\"{&quot;strokeWidth&quot;:1,&quot;rotation&quot;:9.054082566192164,&quot;deleteIcon&quot;:null,&quot;rotationIcon&quot;:null,&quot;group&quot;:null,&quot;editable&quot;:true,&quot;annotation&quot;:null}\\\" id=\\\"rectangle_068cb630-dcca-4335-8abb-fb085e1893dd\\\" fill-opacity=\\\"0\\\" fill=\\\"#00bfff\\\" fill-rule=\\\"nonzero\\\" stroke=\\\"#00bfff\\\" stroke-width=\\\"1\\\" stroke-linecap=\\\"butt\\\" stroke-linejoin=\\\"miter\\\" stroke-miterlimit=\\\"10\\\" stroke-dasharray=\\\"\\\" stroke-dashoffset=\\\"0\\\" font-family=\\\"none\\\" font-weight=\\\"none\\\" font-size=\\\"none\\\" text-anchor=\\\"none\\\" style=\\\"mix-blend-mode: normal\\\"/></svg>\"}},\"within\":{\"@id\":\"https://diyhistory.org/toyo/omekac3/oa/collections/27/manifest.json\",\"@type\":\"sc:Manifest\"}}],\"@id\":\"https://diyhistory.org/toyo/omekac3/oa/items/5697/anno.json\"}"
        }
    ],
    "extended_resources": [],
    "featured": false,
    "files": {
        "count": 0,
        "resource": "files",
        "url": "https://diyhistory.org/toyo/omekac3/api/files?item=5697"
    },
    "id": 5697,
    "item_type": {
        "id": 18,
        "name": "Annotation",
        "resource": "item_types",
        "url": "https://diyhistory.org/toyo/omekac3/api/item_types/18"
    },
    "modified": "2021-02-22T06:36:51+00:00",
    "owner": {
        "id": 5,
        "resource": "users",
        "url": "https://diyhistory.org/toyo/omekac3/api/users/5"
    },
    "public": false,
    "tags": [],
    "url": "https://diyhistory.org/toyo/omekac3/api/items/5697"
}